{
"skeleton": {
	"hash": "zrRSAfIdZV/Cyisgd3UVriSC+k4",
	"spine": "3.8.99",
	"x": -323.54,
	"y": 4.7,
	"width": 678.9,
	"height": 873.43,
	"images": "./images/",
	"audio": ""
},
"bones": [
	{ "name": "root" },
	{ "name": "stomach", "parent": "root", "length": 108.42, "rotation": 88.26, "x": 15.29, "y": 267.89 },
	{ "name": "chest", "parent": "stomach", "length": 171, "rotation": -3.08, "x": 113.09 },
	{ "name": "neck", "parent": "chest", "length": 57.83, "rotation": 11.47, "x": 171, "transform": "noScale" },
	{ "name": "head", "parent": "neck", "length": 149.99, "rotation": 104.04, "x": 57.83, "transform": "noRotationOrReflection" },
	{
		"name": "shoulder_l",
		"parent": "chest",
		"length": 147.02,
		"rotation": -100.67,
		"x": 168.22,
		"y": -1.2,
		"transform": "noScale"
	},
	{
		"name": "shoulder_r",
		"parent": "chest",
		"length": 141.2,
		"rotation": 103,
		"x": 164.16,
		"y": 1.35,
		"transform": "noScale"
	},
	{ "name": "arm_l", "parent": "shoulder_l", "length": 150.27, "rotation": -24.09, "x": 150.45, "y": 1.94 },
	{ "name": "forearm_l", "parent": "arm_l", "length": 89.77, "rotation": -57.78, "x": 150.27 },
	{ "name": "hand_l_1", "parent": "forearm_l", "length": 76.98, "rotation": 28.49, "x": 89.77 },
	{ "name": "hand_l_2", "parent": "hand_l_1", "length": 84.62, "rotation": -43.06, "x": 76.98 },
	{ "name": "arm_r", "parent": "shoulder_r", "length": 118.2, "rotation": 72.96, "x": 139.17, "y": -0.68 },
	{ "name": "forearm_r", "parent": "arm_r", "length": 122.57, "rotation": -37.73, "x": 118.2 },
	{
		"name": "hand_r",
		"parent": "forearm_r",
		"length": 94.57,
		"rotation": -122.41,
		"x": 122.57,
		"transform": "noRotationOrReflection",
		"color": "abe323ff"
	},
	{
		"name": "sword",
		"parent": "root",
		"length": 621.34,
		"rotation": 95.78,
		"x": -246.46,
		"y": 149,
		"skin": true
	},
	{
		"name": "bone15",
		"parent": "stomach",
		"length": 99.27,
		"rotation": -99.96,
		"x": -0.34,
		"y": 2.29,
		"color": "abe323ff"
	},
	{ "name": "thig_l", "parent": "bone15", "length": 79.33, "rotation": -68.7, "x": 99.27 },
	{ "name": "main", "parent": "root" },
	{ "name": "foot_l", "parent": "main", "length": 163.36, "rotation": -174.26, "x": 198.27, "y": 16.51 },
	{ "name": "calf_l", "parent": "thig_l", "length": 131.99, "rotation": 20.77, "x": 79.33 },
	{
		"name": "foot_l2",
		"parent": "foot_l",
		"length": 61.71,
		"rotation": -1.46,
		"x": 4.2,
		"y": -39.48,
		"color": "ff3f00ff"
	},
	{
		"name": "foot_l3",
		"parent": "foot_l",
		"length": 92.97,
		"rotation": 2.44,
		"x": 65.89,
		"y": -41.05,
		"color": "ff3f00ff"
	},
	{ "name": "pelvis_r", "parent": "stomach", "length": 60.04, "rotation": 96.68, "x": 0.82, "y": 1.75 },
	{ "name": "thig_r", "parent": "pelvis_r", "length": 76.98, "rotation": 46.73, "x": 60.04 },
	{ "name": "calf_r", "parent": "thig_r", "length": 102.97, "rotation": 74.24, "x": 76.98 },
	{ "name": "foot_r", "parent": "main", "length": 145.45, "rotation": -170.01, "x": -28.98, "y": 64.61 },
	{
		"name": "foot_r2",
		"parent": "foot_r",
		"length": 47.02,
		"rotation": -2.26,
		"x": 1.78,
		"y": -34.34,
		"color": "ff3f00ff"
	},
	{
		"name": "foot_r3",
		"parent": "foot_r",
		"length": 89.36,
		"rotation": 0.02,
		"x": 48.86,
		"y": -35.63,
		"color": "ff3f00ff"
	},
	{ "name": "hand_r2", "parent": "root", "rotation": 20.73, "x": -221.28, "y": 320.28, "color": "ff3f00ff" },
	{ "name": "hand_l", "parent": "root", "x": 206.43, "y": 326.64, "color": "ff3f00ff" },
	{ "name": "eyes", "parent": "head", "x": 19, "y": 117.69 },
	{ "name": "eye_l", "parent": "eyes", "x": 0.13, "y": -70.26 },
	{ "name": "eye_r", "parent": "eyes", "x": 22.12, "y": 21.01 },
	{
		"name": "belt",
		"parent": "stomach",
		"length": 41.34,
		"rotation": -177.97,
		"x": -9.3,
		"y": 26.8,
		"color": "abe323ff"
	},
	{ "name": "belt2", "parent": "belt", "length": 41.34, "x": 41.34, "color": "abe323ff" },
	{ "name": "belt3", "parent": "belt2", "length": 41.34, "x": 41.34, "color": "abe323ff" },
	{ "name": "shadow", "parent": "root", "x": 8.25, "y": 56.41, "scaleX": 4.9608, "scaleY": 3.9158 }
],
"slots": [
	{ "name": "shadow_hard", "bone": "shadow", "attachment": "shadow" },
	{ "name": "foot_r", "bone": "foot_r", "attachment": "foot_r" },
	{ "name": "foot_l", "bone": "foot_l", "attachment": "foot_l" },
	{ "name": "calf-back-red", "bone": "calf_l", "attachment": "calf_l" },
	{ "name": "thigh-back-red", "bone": "thig_l", "attachment": "thigh_l" },
	{ "name": "forearm-red", "bone": "forearm_r", "attachment": "forearm_r" },
	{ "name": "hand-2-red", "bone": "hand_r", "attachment": "hand-2-r" },
	{ "name": "arm-red", "bone": "arm_r", "attachment": "arm_r" },
	{ "name": "calf-red", "bone": "calf_r", "attachment": "calf_r" },
	{ "name": "foot-red", "bone": "root" },
	{ "name": "foot-red2", "bone": "root" },
	{ "name": "thigh-red", "bone": "thig_r", "attachment": "thigh_r" },
	{ "name": "hand-sword-red", "bone": "sword", "attachment": "weapon" },
	{ "name": "hand-red", "bone": "hand_r", "attachment": "hand-r" },
	{ "name": "finger-red", "bone": "hand_r", "attachment": "finger_r" },
	{ "name": "skirt", "bone": "root", "attachment": "skirt" },
	{ "name": "spine", "bone": "chest", "attachment": "spine" },
	{ "name": "belt-2", "bone": "stomach", "attachment": "belt-2" },
	{ "name": "belt", "bone": "stomach", "attachment": "belt" },
	{ "name": "eyeball", "bone": "head", "attachment": "eyeball" },
	{ "name": "pupil", "bone": "eye_r", "attachment": "pupil" },
	{ "name": "blink", "bone": "head", "attachment": "blink" },
	{ "name": "eyeball-back", "bone": "head", "attachment": "eyeball-back" },
	{ "name": "pupil2", "bone": "eye_l", "attachment": "pupil2" },
	{ "name": "blink2", "bone": "head", "attachment": "blink2" },
	{ "name": "head-red", "bone": "head", "attachment": "head" },
	{ "name": "hand-back-red", "bone": "hand_l_1", "attachment": "hand_l" },
	{ "name": "eyes-closed-red", "bone": "head" },
	{ "name": "arm-back-red", "bone": "arm_l", "attachment": "arm_l" },
	{ "name": "forearm-back-red", "bone": "forearm_l", "attachment": "forearm_l" },
	{ "name": "shoulder-back", "bone": "shoulder_l", "attachment": "shoulder-back" }
],
"ik": [
	{
		"name": "foot_l2",
		"order": 4,
		"bones": [ "thig_l", "calf_l" ],
		"target": "foot_l2"
	},
	{
		"name": "foot_l3",
		"order": 3,
		"bones": [ "foot_l2" ],
		"target": "foot_l3"
	},
	{
		"name": "foot_r2",
		"order": 2,
		"bones": [ "thig_r", "calf_r" ],
		"target": "foot_r2"
	},
	{
		"name": "foot_r3",
		"bones": [ "foot_r2" ],
		"target": "foot_r3"
	},
	{
		"name": "hand_l",
		"order": 6,
		"bones": [ "arm_l", "forearm_l" ],
		"target": "hand_l",
		"bendPositive": false
	},
	{
		"name": "hand_r",
		"order": 5,
		"bones": [ "arm_r", "forearm_r" ],
		"target": "hand_r2",
		"bendPositive": false
	}
],
"transform": [
	{
		"name": "pelvis_l",
		"order": 1,
		"bones": [ "pelvis_r" ],
		"target": "bone15",
		"rotation": -163.35,
		"x": 0.33,
		"y": 1.24,
		"translateMix": -1,
		"scaleMix": 0,
		"shearMix": 0
	},
	{
		"name": "tk_sword",
		"order": 7,
		"bones": [ "sword" ],
		"target": "hand_r",
		"rotation": -121.07,
		"x": 122.88,
		"y": 121.95,
		"scaleMix": 0,
		"shearMix": 0
	}
],
"skins": [
	{
		"name": "body/green",
		"attachments": {
			"arm-back-red": {
				"arm_l": {
					"name": "green/arm-back-red",
					"type": "mesh",
					"uvs": [ 0.27561, 0, 0.50948, 0.01452, 1, 0.6772, 1, 0.81961, 0.95118, 0.95092, 0.64117, 1, 0.48199, 1, 0.02633, 0.52286, 0, 0.36571, 0, 0.24461, 0.15016, 0, 0.72553, 0.78527, 0.21935, 0.24418 ],
					"triangles": [ 4, 11, 3, 5, 11, 4, 12, 10, 0, 9, 10, 12, 8, 9, 12, 7, 8, 12, 11, 1, 2, 11, 2, 3, 12, 1, 11, 1, 12, 0, 6, 12, 11, 7, 12, 6, 5, 6, 11 ],
					"vertices": [ 1, 7, -44.33, 43.74, 1, 2, 7, -0.91, 76.01, 0.99997, 8, -144.91, -87.38, 3.0E-5, 2, 7, 167.49, 50.11, 0.66135, 8, -33.22, 41.28, 0.33865, 2, 7, 184.91, 29.04, 0.29347, 8, -6.1, 44.78, 0.70653, 2, 7, 192.27, 2.42, 0.02096, 8, 20.35, 36.83, 0.97904, 2, 7, 143.08, -50.46, 0.53127, 8, 38.86, -32.99, 0.46873, 2, 7, 114.73, -73.89, 0.80599, 8, 43.56, -69.46, 0.19401, 1, 7, -24.76, -70.33, 1, 1, 7, -48.67, -50.94, 1, 1, 7, -63.49, -33.02, 1, 1, 7, -66.67, 25.28, 1, 2, 7, 131.83, -6.27, 0.93432, 8, -4.53, -18.94, 0.06568, 1, 7, -24.48, -0.68, 1 ],
					"hull": 11,
					"edges": [ 0, 20, 0, 2, 2, 4, 4, 6, 6, 8, 8, 10, 10, 12, 12, 14, 14, 16, 16, 18, 18, 20 ],
					"width": 235,
					"height": 196
				}
			},
			"arm-red": {
				"arm_r": {
					"name": "green/arm-red",
					"type": "mesh",
					"uvs": [ 1, 1, 0, 1, 0, 0, 1, 0 ],
					"triangles": [ 1, 2, 3, 1, 3, 0 ],
					"vertices": [ 113.15, 105.53, 151.58, -24.93, -22.04, -76.07, -60.47, 54.39 ],
					"hull": 4,
					"edges": [ 0, 2, 2, 4, 4, 6, 0, 6 ],
					"width": 140,
					"height": 185
				}
			},
			"belt": {
				"belt": { "name": "red/belt", "x": 17.59, "y": -11.75, "rotation": -88.26, "width": 242, "height": 98 }
			},
			"belt-2": {
				"belt-2": {
					"name": "red/belt-2",
					"type": "mesh",
					"uvs": [ 1, 0.03785, 1, 0.04492, 0.83322, 0.37724, 0.82682, 0.51843, 0.82041, 0.65962, 0.84873, 0.80593, 0.87226, 0.92744, 0.56595, 1, 0.39232, 1, 0, 0.93062, 0, 0.91005, 0.00909, 0.85017, 0.09713, 0.78037, 0.15051, 0.65554, 0.17847, 0.49216, 0.17847, 0.3343, 0.12299, 0.10017, 0.13772, 0.0032, 0.42247, 0.86848, 0.46823, 0.6739, 0.50635, 0.3912, 0.52414, 0.16908 ],
					"triangles": [ 12, 13, 18, 12, 9, 10, 8, 12, 18, 12, 10, 11, 8, 9, 12, 19, 5, 18, 7, 5, 6, 7, 18, 5, 8, 18, 7, 3, 19, 20, 19, 14, 20, 4, 19, 3, 13, 14, 19, 18, 13, 19, 5, 19, 4, 15, 16, 21, 20, 15, 21, 20, 21, 2, 14, 15, 20, 3, 20, 2, 16, 17, 21, 21, 17, 0, 1, 21, 0, 2, 21, 1 ],
					"vertices": [ 1, 1, 19.25, -37.71, 1, 1, 1, 18.11, -37.75, 1, 3, 1, -36.3, -19.87, 0.46094, 33, 28.63, 45.69, 0.35693, 34, -12.71, 45.69, 0.18213, 4, 1, -59.18, -19.82, 0.14077, 33, 51.5, 44.83, 0.2775, 34, 10.16, 44.83, 0.55359, 35, -31.19, 44.83, 0.02814, 4, 1, -82.07, -19.76, 0.0282, 33, 74.37, 43.96, 0.07544, 34, 33.03, 43.96, 0.63235, 35, -8.32, 43.96, 0.26401, 4, 1, -105.66, -23.79, 0.00165, 33, 98.09, 47.16, 0.00571, 34, 56.74, 47.16, 0.30412, 35, 15.4, 47.16, 0.68852, 2, 34, 76.44, 49.81, 0.16184, 35, 35.1, 49.81, 0.83816, 2, 34, 88.02, 13.91, 0.01228, 35, 46.67, 13.91, 0.98772, 1, 35, 46.57, -6.4, 1, 2, 34, 76.44, -52.25, 0.07703, 35, 35.1, -52.25, 0.92297, 2, 34, 73.11, -52.23, 0.0799, 35, 31.76, -52.23, 0.9201, 2, 34, 63.41, -51.12, 0.10704, 35, 22.07, -51.12, 0.89296, 3, 33, 93.5, -40.76, 4.0E-5, 34, 52.16, -40.76, 0.2552, 35, 10.81, -40.76, 0.74476, 3, 33, 73.31, -34.41, 0.03179, 34, 31.97, -34.41, 0.71513, 35, -9.38, -34.41, 0.25308, 3, 33, 46.86, -31.01, 0.43941, 34, 5.52, -31.01, 0.55863, 35, -35.83, -31.01, 0.00196, 2, 33, 21.29, -30.88, 0.95894, 34, -20.06, -30.88, 0.04106, 1, 1, 6.05, 64.54, 1, 1, 1, 21.81, 63.3, 1, 1, 35, 25.28, -2.77, 1, 4, 1, -85.63, 21.36, 3.3E-4, 33, 76.47, 2.74, 7.8E-4, 34, 35.13, 2.74, 0.98054, 35, -6.21, 2.74, 0.01835, 3, 1, -39.72, 18.28, 0.04312, 33, 30.7, 7.44, 0.92261, 34, -10.64, 7.44, 0.03428, 2, 1, -3.69, 17.29, 0.36352, 33, -5.27, 9.7, 0.63648 ],
					"hull": 18,
					"edges": [ 0, 34, 0, 2, 2, 4, 12, 14, 14, 16, 16, 18, 18, 20, 32, 34, 32, 30, 30, 28, 28, 26, 26, 24, 20, 22, 24, 22, 10, 12, 8, 10, 4, 6, 6, 8 ],
					"width": 117,
					"height": 162
				}
			},
			"blink": {
				"blink": { "name": "red/blink", "x": 37.04, "y": 132.27, "rotation": -104.04, "width": 13, "height": 9 }
			},
			"blink2": {
				"blink2": { "name": "red/blink", "x": 19.46, "y": 40.59, "rotation": -104.04, "width": 13, "height": 9 }
			},
			"calf-back-red": {
				"calf_l": {
					"name": "green/calf-back-red",
					"type": "mesh",
					"uvs": [ 0.48387, 0, 0.98981, 0.24722, 0.99056, 0.75393, 0.99066, 0.82861, 0.7499, 1, 0.54421, 1, 0.31736, 0.96495, 0.27435, 0.86816, 0, 0.25078, 0, 0.09019, 0.23425, 0, 0.6708, 0.84443, 0.37915, 0.18583 ],
					"triangles": [ 12, 10, 0, 12, 0, 1, 12, 8, 9, 12, 9, 10, 11, 12, 1, 11, 1, 2, 11, 2, 3, 7, 8, 12, 7, 12, 11, 5, 6, 7, 11, 5, 7, 4, 11, 3, 5, 11, 4 ],
					"vertices": [ -17.49, 41.07, 34.79, 66.74, 91.66, 33.5, 100.04, 28.6, 107.58, -2.6, 97.6, -19.64, 82.66, -36.13, 69.72, -33.33, -12.85, -15.49, -30.86, -4.93, -29.61, 20.4, 86.29, 1.07, -1.73, 20.19 ],
					"hull": 11,
					"edges": [ 0, 20, 0, 2, 6, 8, 8, 10, 10, 12, 16, 18, 18, 20, 12, 14, 14, 16, 2, 4, 4, 6 ],
					"width": 100,
					"height": 134
				}
			},
			"calf-red": {
				"calf_r": {
					"name": "green/calf-red",
					"type": "mesh",
					"uvs": [ 0.55988, 0.11511, 0.86936, 0.43693, 0.97039, 0.542, 0.97415, 0.74984, 0.97791, 0.95769, 0.74853, 0.98113, 0.6191, 0.98113, 0.50524, 0.86023, 0.13821, 0.47046, 0.04269, 0.36903, 0.01802, 0.13449, 0.01802, 0.02585, 0.47774, 0.02969, 0.30267, 0.27184, 0.82153, 0.79469 ],
					"triangles": [ 8, 9, 13, 1, 13, 0, 14, 1, 2, 14, 2, 3, 1, 7, 13, 7, 8, 13, 1, 14, 7, 14, 3, 4, 6, 7, 14, 5, 6, 14, 5, 14, 4, 13, 10, 11, 12, 13, 11, 13, 12, 0, 9, 10, 13 ],
					"vertices": [ 2, 23, 60.61, 24.13, 0.58502, 24, 6.17, 28.5, 0.41498, 2, 23, 87.92, 64.11, 0.14398, 24, 53.95, 36.32, 0.85602, 1, 24, 69.54, 38.87, 1, 1, 24, 87.63, 26.29, 1, 1, 24, 105.72, 13.7, 1, 1, 24, 92.8, -8.38, 1, 1, 24, 84.37, -20.01, 1, 2, 23, 139.38, 32.5, 0.07312, 24, 66.58, -22.73, 0.92688, 2, 23, 106.14, -15.06, 0.30886, 24, 9.22, -31.5, 0.69114, 2, 23, 97.5, -27.44, 0.37021, 24, -5.7, -33.78, 0.62979, 2, 23, 73.54, -34.64, 0.84808, 24, -27.44, -21.42, 0.15192, 2, 23, 62.22, -36.73, 0.93878, 24, -36.77, -14.66, 0.06122, 2, 23, 53.36, 13.52, 0.70208, 24, -6.51, 26.43, 0.29792, 2, 23, 82.13, -0.93, 0.48797, 24, 2.88, -4.37, 0.51203, 1, 24, 81.55, 9.78, 1 ],
					"hull": 13,
					"edges": [ 8, 10, 10, 12, 18, 20, 20, 22, 22, 24, 4, 6, 6, 8, 12, 14, 4, 2, 14, 16, 16, 18, 2, 0, 0, 24 ],
					"width": 111,
					"height": 106
				}
			},
			"eyeball": {
				"eyeball": { "name": "red/eyeball", "x": 40.44, "y": 133.48, "rotation": -104.04, "width": 37, "height": 41 }
			},
			"eyeball-back": {
				"eyeball-back": {
					"name": "red/eyeball-back2",
					"path": "red/eyeball-back",
					"x": 20.55,
					"y": 43.62,
					"rotation": -104.04,
					"width": 51,
					"height": 46
				}
			},
			"eyes-closed-red": {
				"eyes-closed-red": { "name": "green/eyes-closed-red", "x": 29.76, "y": 82.55, "rotation": -104.04, "width": 161, "height": 55 }
			},
			"finger-red": {
				"finger_r": {
					"name": "green/finger-red",
					"type": "mesh",
					"uvs": [ 1, 1, 0, 1, 0, 0, 1, 0 ],
					"triangles": [ 1, 2, 3, 1, 3, 0 ],
					"vertices": [ 13.42, 17.64, 54.22, -12.95, 17.63, -61.76, -23.17, -31.17 ],
					"hull": 4,
					"edges": [ 0, 2, 2, 4, 4, 6, 0, 6 ],
					"width": 55,
					"height": 65
				}
			},
			"foot_l": {
				"foot_l": {
					"name": "green/foot-red",
					"type": "mesh",
					"uvs": [ 0.83555, 0.02062, 0.97907, 0.33641, 0.99087, 0.51066, 0.99087, 0.64572, 0.8262, 0.73399, 0.70872, 0.66774, 0.65513, 0.69135, 0.56007, 0.87666, 0.36845, 0.97938, 0.27909, 0.97938, 0.01679, 0.90173, 0.00913, 0.61233, 0.00913, 0.53151, 0.15178, 0.14873, 0.30244, 0.12021, 0.47603, 0.15419, 0.55708, 0.13058, 0.66578, 0.08807, 0.70034, 0.04489, 0.82857, 0.02062, 0.61366, 0.34969 ],
					"triangles": [ 5, 20, 18, 4, 5, 19, 6, 20, 5, 3, 4, 2, 4, 1, 2, 5, 18, 19, 20, 17, 18, 19, 0, 1, 1, 4, 19, 20, 16, 17, 11, 12, 13, 20, 15, 16, 7, 20, 6, 7, 15, 20, 9, 10, 11, 9, 13, 14, 8, 9, 14, 15, 8, 14, 9, 11, 13, 7, 8, 15 ],
					"vertices": [ 1, 19, 82.08, 12.11, 1, 2, 19, 127.51, 24.6, 0.73786, 20, -20.13, -14.84, 0.26214, 1, 20, -21.54, 3.47, 1, 1, 20, -20.49, 17.49, 1, 1, 20, 18.8, 23.77, 1, 2, 21, -14.83, 15.88, 0.01376, 20, 45.84, 14.83, 0.98624, 2, 21, -2.01, 16.52, 0.38242, 20, 58.59, 16.35, 0.61758, 2, 21, 22.86, 32.44, 0.99464, 20, 82.32, 33.92, 0.00536, 1, 21, 68.98, 36.62, 1, 1, 21, 89.78, 33.63, 1, 1, 21, 149.68, 16.85, 1, 1, 21, 147.17, -13.24, 1, 1, 21, 145.97, -21.57, 1, 1, 21, 107.1, -56.26, 1, 2, 21, 71.61, -54.16, 0.9996, 19, 27.66, -101.29, 4.0E-4, 3, 21, 31.72, -44.84, 0.91262, 19, 51.35, -67.86, 0.05037, 20, 96.41, -42.58, 0.03701, 3, 21, 12.5, -44.57, 0.66007, 19, 58.86, -50.18, 0.17339, 20, 77.22, -43.61, 0.16654, 3, 21, -13.42, -45.31, 0.16524, 19, 67.96, -25.89, 0.58344, 20, 51.41, -46.12, 0.25133, 3, 21, -22.11, -48.61, 0.0671, 19, 68.19, -16.6, 0.77093, 20, 42.97, -50, 0.16197, 2, 21, -52.31, -46.82, 1.0E-5, 19, 81.25, 10.69, 0.99999, 3, 21, 2.58, -20.09, 0.51658, 19, 85.27, -50.23, 0.13948, 20, 65.66, -19.86, 0.34394 ],
					"hull": 20,
					"edges": [ 0, 38, 0, 2, 2, 4, 4, 6, 16, 18, 18, 20, 20, 22, 22, 24, 24, 26, 6, 8, 8, 10, 10, 12, 14, 16, 12, 14, 26, 28, 28, 30, 30, 32, 32, 34, 36, 38, 34, 36 ],
					"width": 219,
					"height": 97
				}
			},
			"foot_r": {
				"foot_r": {
					"name": "green/foot-red",
					"type": "mesh",
					"uvs": [ 0.83555, 0.02062, 0.97907, 0.33641, 0.99087, 0.51066, 0.99087, 0.64572, 0.8262, 0.73399, 0.70872, 0.66774, 0.65513, 0.69135, 0.56007, 0.87666, 0.36845, 0.97938, 0.27909, 0.97938, 0.01679, 0.90173, 0.00913, 0.61233, 0.00913, 0.53151, 0.15178, 0.14873, 0.30244, 0.12021, 0.47603, 0.15419, 0.55708, 0.13058, 0.66578, 0.08807, 0.70034, 0.04489, 0.82857, 0.02062, 0.61366, 0.34969 ],
					"triangles": [ 11, 12, 13, 7, 20, 6, 7, 15, 20, 9, 10, 11, 9, 13, 14, 8, 9, 14, 15, 8, 14, 9, 11, 13, 7, 8, 15, 1, 4, 19, 20, 16, 17, 5, 20, 18, 4, 5, 19, 6, 20, 5, 3, 4, 2, 20, 15, 16, 4, 1, 2, 5, 18, 19, 20, 17, 18, 19, 0, 1 ],
					"vertices": [ 1, 24, 71.36, 26.37, 1, 2, 24, 114.6, 33.86, 0.13714, 26, -35.34, -5.74, 0.86286, 1, 26, -35.63, 11.36, 1, 1, 26, -33.87, 24.34, 1, 1, 26, 3.02, 27.97, 1, 2, 26, 27.65, 18.14, 0.78886, 27, -18.73, 18.33, 0.21114, 2, 26, 39.59, 18.83, 0.25059, 27, -6.77, 18.55, 0.74941, 1, 27, 16.85, 32.63, 1, 1, 27, 59.91, 35.15, 1, 1, 27, 79.18, 31.75, 1, 1, 27, 134.44, 14.35, 1, 1, 27, 131.21, -13.59, 1, 1, 27, 129.85, -21.31, 1, 2, 26, 141.74, -48.16, 0.00795, 27, 92.64, -52.44, 0.99205, 3, 24, 10.71, -73.86, 0.00227, 26, 108.67, -46.46, 0.0724, 27, 59.66, -49.43, 0.92533, 3, 24, 35.67, -45, 0.09054, 26, 71.44, -38.07, 0.44022, 27, 22.8, -39.58, 0.46925, 3, 24, 44.23, -29.28, 0.27149, 26, 53.55, -37.96, 0.61197, 27, 4.92, -38.75, 0.11655, 2, 24, 54.85, -7.58, 0.84423, 26, 29.4, -38.84, 0.15577, 1, 24, 55.9, 1.01, 1, 1, 24, 70.46, 25.13, 1, 3, 24, 68.71, -31.71, 0.18174, 26, 44.13, -15.23, 0.80865, 27, -3.59, -15.67, 0.00962 ],
					"hull": 20,
					"edges": [ 0, 38, 0, 2, 2, 4, 4, 6, 16, 18, 18, 20, 20, 22, 22, 24, 24, 26, 6, 8, 8, 10, 10, 12, 14, 16, 12, 14, 26, 28, 28, 30, 30, 32, 32, 34, 36, 38, 34, 36 ],
					"width": 219,
					"height": 97
				}
			},
			"forearm-back-red": {
				"forearm_l": {
					"name": "green/forearm-back-red",
					"type": "mesh",
					"uvs": [ 1, 1, 0, 1, 0, 0, 1, 0 ],
					"triangles": [ 1, 2, 3, 1, 3, 0 ],
					"vertices": [ 99.91, 87.7, 119.88, -67.01, -32.86, -86.72, -52.82, 68 ],
					"hull": 4,
					"edges": [ 0, 2, 2, 4, 4, 6, 0, 6 ],
					"width": 160,
					"height": 158
				}
			},
			"forearm-red": {
				"forearm_r": {
					"name": "green/forearm-red",
					"type": "mesh",
					"uvs": [ 1, 1, 0, 1, 0, 0, 1, 0 ],
					"triangles": [ 1, 2, 3, 1, 3, 0 ],
					"vertices": [ 72.86, 121.37, 182.82, -2.98, 59.97, -111.62, -50, 12.73 ],
					"hull": 4,
					"edges": [ 0, 2, 2, 4, 4, 6, 0, 6 ],
					"width": 170,
					"height": 168
				}
			},
			"hand-2-red": {
				"hand-2-r": {
					"name": "green/hand-2-red",
					"type": "mesh",
					"uvs": [ 0.4481, 0, 0.76085, 0.0684, 1, 0.51838, 1, 0.7224, 0.68504, 1, 0.48848, 1, 0.01118, 0.96113, 0.01013, 0.22209, 0.28961, 0, 0.50752, 0.50331 ],
					"triangles": [ 9, 0, 1, 3, 4, 9, 4, 5, 9, 5, 6, 9, 9, 7, 8, 8, 0, 9, 9, 6, 7, 9, 2, 3, 9, 1, 2 ],
					"vertices": [ 2, 13, 8.57, -49.96, 0.07708, 12, 120.86, -50.66, 0.92292, 1, 12, 107.6, -24.82, 1, 2, 13, 1.47, 23.38, 0.65928, 12, 128.73, 22.6, 0.34072, 2, 13, 14.32, 40.53, 0.64525, 12, 144.78, 36.8, 0.35475, 1, 13, 54.49, 46.85, 1, 1, 13, 68.64, 36.23, 1, 1, 13, 100.56, 7.2, 1, 2, 13, 54.1, -54.94, 0.83992, 12, 164.44, -64.74, 0.16008, 2, 13, 19.98, -58.52, 0.63826, 12, 130.31, -61.35, 0.36174, 2, 13, 35.99, -4.47, 0.99114, 12, 156.91, -11.65, 0.00886 ],
					"hull": 9,
					"edges": [ 0, 16, 0, 2, 2, 4, 4, 6, 6, 8, 8, 10, 10, 12, 12, 14, 14, 16 ],
					"width": 94,
					"height": 109
				}
			},
			"hand-back-red": {
				"hand_l": {
					"name": "green/hand-back-red",
					"type": "mesh",
					"uvs": [ 0.65626, 0, 0.9054, 0.1045, 1, 0.58586, 1, 0.59958, 0.84786, 0.82213, 0.44745, 0.98644, 0.26553, 0.99939, 0.16501, 0.86882, 0.20388, 0.64169, 0.03839, 0.70436, 0.00183, 0.65687, 0.00874, 0.2272, 0.44265, 0, 0.70413, 0.51135, 0.30742, 0.4845 ],
					"triangles": [ 6, 7, 5, 7, 8, 5, 5, 8, 13, 5, 13, 4, 13, 8, 14, 4, 13, 3, 8, 10, 14, 13, 2, 3, 13, 14, 12, 14, 10, 11, 13, 1, 2, 14, 11, 12, 9, 10, 8, 1, 13, 0, 12, 0, 13 ],
					"vertices": [ 2, 8, 42.12, 12.06, 0.95745, 9, -36.12, 33.33, 0.04255, 2, 8, 61, 61.72, 0.41568, 9, 4.16, 67.97, 0.58432, 1, 9, 118.33, 42.9, 1, 2, 9, 121.4, 41.71, 0.34414, 10, 3.98, 60.8, 0.65586, 2, 9, 160.9, -4.23, 0.00404, 10, 64.21, 54.21, 0.99596, 1, 10, 128.89, -0.9, 1, 2, 9, 161.1, -121.69, 1.5E-4, 10, 144.55, -31.47, 0.99985, 3, 8, 260.74, -52.85, 1.1E-4, 9, 125.05, -128.01, 0.01286, 10, 122.53, -60.7, 0.98702, 3, 8, 205.74, -52.58, 0.0334, 9, 76.85, -101.54, 0.20328, 10, 69.23, -74.27, 0.76333, 3, 8, 224.64, -81.51, 0.02312, 9, 79.65, -135.98, 0.69761, 10, 94.8, -97.52, 0.27927, 3, 8, 214.22, -89.79, 0.02728, 9, 66.54, -138.28, 0.6653, 10, 86.79, -108.15, 0.30741, 1, 9, -29.17, -99.88, 1, 3, 8, 47.26, -27.77, 0.99521, 9, -50.61, -4.13, 4.2E-4, 10, -90.4, -90.13, 0.00437, 1, 10, 5.1, 1.3, 1, 3, 8, 165.84, -38.1, 0.06304, 9, 48.68, -69.77, 0.376, 10, 26.97, -70.3, 0.56096 ],
					"hull": 13,
					"edges": [ 0, 24, 0, 2, 2, 4, 4, 6, 6, 8, 8, 10, 10, 12, 20, 22, 22, 24, 12, 14, 14, 16, 18, 20, 16, 18 ],
					"width": 192,
					"height": 244
				}
			},
			"hand-red": {
				"hand-r": {
					"name": "green/hand-red",
					"type": "mesh",
					"uvs": [ 1, 1, 0, 1, 0, 0, 1, 0 ],
					"triangles": [ 1, 2, 3, 1, 3, 0 ],
					"vertices": [ 50.41, 58.65, 123.22, 4.07, 56.04, -85.55, -16.77, -30.96 ],
					"hull": 4,
					"edges": [ 0, 2, 2, 4, 4, 6, 0, 6 ],
					"width": 95,
					"height": 116
				}
			},
			"head-red": {
				"head": {
					"name": "green/head-red",
					"type": "mesh",
					"uvs": [ 1, 1, 0, 1, 0, 0, 1, 0 ],
					"triangles": [ 1, 2, 3, 1, 3, 0 ],
					"vertices": [ -186.21, -119.6, -99.63, 226.74, 308.8, 124.63, 222.22, -221.71 ],
					"hull": 4,
					"edges": [ 0, 2, 2, 4, 4, 6, 0, 6 ],
					"width": 361,
					"height": 425
				}
			},
			"pupil": {
				"pupil": { "name": "red/pupil", "x": -1.16, "y": -0.97, "rotation": -104.04, "width": 13, "height": 24 }
			},
			"pupil2": {
				"pupil2": { "name": "red/pupil", "x": -0.1, "y": -1.18, "rotation": -104.04, "width": 13, "height": 24 }
			},
			"shoulder-back": {
				"shoulder-back": { "name": "red/shoulder-back", "x": 111.74, "y": 51.88, "rotation": 15.48, "width": 230, "height": 213 }
			},
			"skirt": {
				"skirt": {
					"name": "red/skirt",
					"type": "mesh",
					"uvs": [ 0.80349, 0.02284, 0.86176, 0.18603, 0.92004, 0.34923, 1, 0.57315, 1, 0.61137, 0.87969, 0.70053, 0.75937, 0.7897, 0.5958, 0.91093, 0.47562, 1, 0.39971, 1, 0.27639, 0.92137, 0.1382, 0.73413, 0, 0.54689, 0, 0.53574, 0.03655, 0.44669, 0.12679, 0.22683, 0.21703, 0.00697, 0.73462, 0.44102, 0.82182, 0.38647, 0.18427, 0.52285, 0.34151, 0.70598, 0.50733, 0.77222, 0.6417, 0.64754 ],
					"triangles": [ 10, 20, 9, 11, 19, 10, 10, 19, 20, 12, 14, 11, 11, 14, 19, 16, 21, 20, 12, 13, 14, 14, 15, 19, 16, 20, 19, 19, 15, 16, 7, 22, 6, 6, 18, 5, 6, 17, 18, 4, 5, 3, 5, 18, 2, 5, 2, 3, 18, 1, 2, 18, 0, 1, 22, 17, 6, 22, 21, 16, 17, 22, 16, 17, 0, 18, 17, 16, 0, 8, 21, 7, 8, 9, 21, 9, 20, 21, 7, 21, 22 ],
					"vertices": [ 5, 1, 51.97, -106.74, 3.0E-4, 15, 100.63, 57.26, 0.37664, 16, -52.85, 22.07, 0.28967, 22, -112.15, -24.94, 0.09439, 23, -136.18, 108.28, 0.23899, 5, 1, 32.35, -127.04, 2.0E-4, 15, 124.02, 41.45, 0.34562, 16, -29.63, 38.12, 0.54301, 22, -130.03, -3.09, 0.04515, 23, -132.53, 136.28, 0.06601, 4, 1, 12.72, -147.34, 1.0E-4, 15, 147.42, 25.63, 0.21523, 16, -6.39, 54.17, 0.78464, 22, -147.91, 18.77, 4.0E-5, 3, 15, 179.51, 3.92, 0.06727, 16, 25.5, 76.19, 0.93273, 22, -172.44, 48.76, 1.0E-5, 3, 1, -18.95, -175.34, 0.00178, 15, 180.47, -0.72, 0.01711, 16, 30.17, 75.4, 0.98112, 4, 1, -31.24, -135.02, 0.05585, 15, 142.89, -19.79, 0.05657, 16, 34.29, 33.46, 0.8843, 23, -86.24, 180.59, 0.00328, 5, 1, -43.73, -94.71, 0.18985, 15, 105.35, -39.08, 0.11365, 16, 38.62, -8.52, 0.6701, 22, -89.07, 68.72, 0.00175, 23, -52.18, 155.67, 0.02465, 5, 1, -66.49, -39.91, 0.38964, 15, 55.31, -70.98, 0.15559, 16, 50.16, -66.73, 0.36562, 22, -31.99, 84.94, 0.00833, 23, -1.23, 125.23, 0.08082, 5, 1, -82.08, 0.36, 0.5104, 15, 18.35, -93.3, 0.11767, 16, 57.53, -109.28, 0.14106, 22, 9.82, 95.74, 0.01832, 23, 35.29, 102.19, 0.21255, 5, 1, -81.59, 26.01, 0.47128, 15, -7, -97.25, 0.0621, 16, 52.01, -134.33, 0.02258, 22, 35.23, 92.26, 0.0248, 23, 50.17, 81.3, 0.41923, 5, 1, -67.85, 67.97, 0.29528, 15, -50.7, -90.98, 0.01184, 16, 30.29, -172.77, 0.00382, 22, 75.31, 73.74, 0.02164, 23, 64.16, 39.43, 0.66742, 5, 1, -42.99, 115.36, 0.12045, 15, -101.68, -74.7, 0.00151, 16, -3.39, -214.35, 6.5E-4, 22, 119.49, 43.54, 0.01165, 23, 72.45, -13.44, 0.86574, 3, 1, -21.2, 162.75, 0.02556, 22, 164.02, 16.38, 0.00341, 23, 83.2, -64.48, 0.97103, 2, 22, 163.9, 15, 0.00414, 23, 82.12, -65.34, 0.99586, 3, 15, -142.55, -46.76, 2.0E-5, 22, 150.64, 5.07, 0.05336, 23, 65.79, -62.5, 0.94662, 5, 1, 19.77, 121.12, 1.0E-4, 15, -118.21, -13.88, 0.08952, 16, -66.06, -207.66, 0.02151, 22, 117.91, -19.47, 0.10261, 23, 25.49, -55.47, 0.78627, 5, 1, 47.94, 91.46, 2.0E-4, 15, -93.87, 19, 0.2287, 16, -87.86, -173.04, 0.10443, 22, 85.17, -44, 0.14359, 23, -14.81, -48.45, 0.52308, 1, 15, 88.35, 1.77, 1, 3, 15, 115.84, 14.37, 0.2552, 16, -7.37, 20.67, 0.74478, 22, -114.43, 20.51, 2.0E-5, 1, 23, 42.24, -17.47, 1, 4, 1, -42.02, 46.77, 0.34469, 16, 9.13, -146.91, 2.0E-4, 22, 51.26, 50.55, 0.14572, 23, 30.78, 41.05, 0.5094, 5, 1, -53.3, -9.5, 0.70239, 15, 23.08, -63.24, 0.17164, 16, 31.25, -93.96, 0.03483, 22, -3.32, 68.3, 0.00955, 23, 6.3, 92.95, 0.0816, 4, 1, -29.26, -54.42, 0.16192, 15, 63.17, -31.8, 0.64283, 16, 16.51, -45.18, 0.19258, 23, -39.78, 114.7, 0.00266 ],
					"hull": 17,
					"edges": [ 0, 32, 6, 8, 16, 18, 18, 20, 24, 26, 14, 16, 12, 14, 20, 22, 22, 24, 8, 10, 10, 12, 4, 6, 0, 2, 2, 4, 26, 28, 28, 30, 30, 32 ],
					"width": 338,
					"height": 124
				}
			},
			"spine": {
				"spine": {
					"name": "red/spine",
					"type": "mesh",
					"uvs": [ 0.64681, 0.29005, 0.6944, 0.30207, 0.746, 0.3479, 0.79759, 0.39372, 0.76748, 0.48023, 0.73859, 0.53429, 0.7097, 0.58836, 0.68343, 0.63753, 0.65786, 0.68537, 0.52296, 0.70392, 0.44341, 0.66918, 0.42327, 0.63469, 0.38716, 0.57284, 0.35207, 0.51273, 0.32761, 0.47083, 0.30315, 0.42892, 0.31231, 0.31949, 0.36756, 0.30873, 0.46728, 0.28932, 0.56699, 0.2699, 0.54428, 0.63787, 0.52013, 0.58762, 0.51047, 0.51063, 0.50564, 0.42554, 0.53655, 0.33721, 0.63121, 0.40528, 0.38588, 0.40852 ],
					"triangles": [ 26, 17, 18, 26, 18, 24, 16, 17, 26, 23, 26, 24, 15, 16, 26, 14, 15, 26, 13, 14, 26, 26, 22, 13, 22, 26, 23, 10, 11, 20, 8, 20, 7, 6, 21, 22, 12, 22, 21, 11, 12, 21, 7, 21, 6, 20, 21, 7, 11, 21, 20, 9, 10, 20, 9, 20, 8, 12, 13, 22, 5, 6, 22, 24, 18, 19, 0, 24, 19, 23, 24, 25, 22, 23, 25, 25, 0, 1, 25, 1, 2, 25, 24, 0, 3, 25, 2, 4, 25, 3, 5, 25, 4, 22, 25, 5 ],
					"vertices": [ 2, 5, 46.56, 81.99, 0.6862, 2, 240.18, -62.13, 0.3138, 2, 5, 84.37, 81.16, 0.89273, 2, 232.36, -99.13, 0.10727, 2, 5, 133.31, 51.58, 0.99616, 2, 194.24, -141.75, 0.00384, 3, 5, 182.25, 22.01, 0.99992, 1, 272.4, -192.49, 4.0E-5, 15, 146.95, 289.21, 4.0E-5, 4, 5, 181.29, -60.5, 0.7712, 2, 75.21, -168.16, 0.12414, 1, 192.48, -171.96, 0.05986, 15, 140.55, 206.94, 0.0448, 4, 5, 173.58, -115.19, 0.35714, 2, 22.9, -150.45, 0.18198, 1, 141.19, -151.47, 0.34631, 15, 129.25, 152.88, 0.11457, 4, 5, 165.89, -169.95, 0.13015, 2, -29.5, -132.76, 0.11602, 1, 89.82, -130.98, 0.51603, 15, 117.96, 98.74, 0.2378, 4, 5, 158.33, -217.48, 0.0551, 2, -74.8, -116.53, 0.05135, 1, 45.46, -112.35, 0.24629, 15, 107.28, 51.82, 0.64726, 4, 5, 150.51, -261.78, 0.00587, 2, -116.89, -100.64, 0.0035, 1, 4.29, -94.21, 0.03703, 15, 96.55, 8.13, 0.9536, 2, 1, -27.54, 7.89, 0.92961, 22, 10.95, 40.69, 0.07039, 5, 2, -116.13, 63.21, 3.4E-4, 1, 13.86, 69.36, 0.04888, 15, -66.21, -10.75, 6.0E-5, 22, 67.18, -7.57, 0.94734, 6, 123.34, 259.19, 0.00339, 5, 2, -89.23, 80.94, 0.01988, 1, 41.67, 85.62, 0.27372, 15, -87.04, 13.83, 3.0E-5, 22, 80.1, -37.09, 0.67794, 6, 134.57, 228.99, 0.02844, 5, 2, -36.79, 112.97, 0.18649, 1, 95.75, 114.79, 0.3605, 15, -125.12, 62.05, 1.0E-5, 22, 102.78, -94.2, 0.26686, 6, 153.98, 170.69, 0.18614, 5, 2, 17.99, 144.3, 0.23822, 1, 152.14, 143.13, 0.15744, 15, -162.8, 112.69, 1.0E-5, 22, 124.36, -153.5, 0.08895, 6, 172.18, 110.26, 0.51538, 4, 2, 55.61, 166.12, 0.13011, 1, 190.88, 162.89, 0.05925, 22, 139.48, -194.27, 0.03336, 6, 184.97, 68.7, 0.77728, 4, 2, 92.5, 187.89, 0.03631, 1, 228.89, 182.65, 0.01548, 22, 154.68, -234.33, 0.00906, 6, 197.89, 27.85, 0.93915, 1, 6, 176.82, -69.6, 1, 2, 2, 205.45, 148.21, 0.01586, 6, 133.81, -73.27, 0.98414, 2, 2, 229.37, 74.07, 0.34347, 6, 56.19, -79.9, 0.65653, 3, 5, -16.85, 83.39, 0.17303, 2, 253.29, -0.07, 0.73088, 6, -21.43, -86.52, 0.09609, 3, 5, 58.57, -255.04, 2.4E-4, 1, 32.68, -6.51, 0.94168, 15, 5.26, 20.92, 0.05808, 4, 2, -49.49, 10.59, 1.4E-4, 1, 77.57, 13.24, 0.94908, 22, 4.03, -64.33, 0.04596, 6, 57.08, 206.09, 0.00482, 4, 2, 31.49, 24.43, 0.49824, 1, 159.17, 22.7, 0.46379, 22, 3.93, -146.47, 0.00827, 6, 52.34, 124.08, 0.0297, 4, 2, 108.7, 34.6, 0.62298, 1, 236.82, 28.71, 2.4E-4, 22, 0.87, -224.3, 0.0011, 6, 44.88, 46.56, 0.37568, 2, 2, 190.52, 17.89, 0.63524, 6, 10.19, -29.4, 0.36476, 4, 5, 63.02, -21.91, 0.79484, 2, 135.03, -59.07, 0.20284, 1, 258.07, -66.24, 0.00107, 15, 25.09, 253.25, 0.00126, 4, 2, 116.35, 126.72, 0.03362, 1, 249.41, 120.28, 0.0065, 22, 90.35, -247.45, 0.0039, 6, 132.91, 18.39, 0.95599 ],
					"hull": 20,
					"edges": [ 6, 8, 16, 18, 18, 20, 30, 32, 14, 16, 12, 14, 8, 10, 10, 12, 20, 22, 22, 24, 24, 26, 26, 28, 28, 30, 32, 34, 34, 36, 36, 38, 2, 0, 0, 38, 2, 4, 4, 6 ],
					"width": 761,
					"height": 907
				}
			},
			"thigh-back-red": {
				"thigh_l": {
					"name": "green/thigh-back-red",
					"type": "mesh",
					"uvs": [ 0.98333, 0.98907, 0.01667, 0.98907, 0.01667, 0.01093, 0.98333, 0.01093 ],
					"triangles": [ 1, 2, 3, 1, 3, 0 ],
					"vertices": [ 124.97, 41.11, 105.63, -73.26, -70.87, -43.42, -51.53, 70.96 ],
					"hull": 4,
					"edges": [ 0, 2, 2, 4, 4, 6, 0, 6 ],
					"width": 120,
					"height": 183
				}
			},
			"thigh-red": {
				"thigh_r": { "name": "green/thigh-red", "x": 24.75, "y": -2.34, "rotation": 128.33, "width": 146, "height": 151 }
			}
		}
	},
	{
		"name": "shadow/hard",
		"attachments": {
			"shadow_hard": {
				"shadow": { "name": "shadow/shadow_hard", "width": 87, "height": 37 }
			}
		}
	},
	{
		"name": "body/red",
		"attachments": {
			"arm-back-red": {
				"arm_l": {
					"name": "red/arm-back-red",
					"type": "mesh",
					"uvs": [ 0.27561, 0, 0.50948, 0.01452, 1, 0.6772, 1, 0.81961, 0.95118, 0.95092, 0.64117, 1, 0.48199, 1, 0.02633, 0.52286, 0, 0.36571, 0, 0.24461, 0.15016, 0, 0.72553, 0.78527, 0.21935, 0.24418 ],
					"triangles": [ 4, 11, 3, 5, 11, 4, 12, 10, 0, 9, 10, 12, 8, 9, 12, 7, 8, 12, 11, 1, 2, 11, 2, 3, 12, 1, 11, 1, 12, 0, 6, 12, 11, 7, 12, 6, 5, 6, 11 ],
					"vertices": [ 1, 7, -44.33, 43.74, 1, 2, 7, -0.91, 76.01, 0.99997, 8, -144.91, -87.38, 3.0E-5, 2, 7, 167.49, 50.11, 0.66135, 8, -33.22, 41.28, 0.33865, 2, 7, 184.91, 29.04, 0.29347, 8, -6.1, 44.78, 0.70653, 2, 7, 192.27, 2.42, 0.02096, 8, 20.35, 36.83, 0.97904, 2, 7, 143.08, -50.46, 0.53127, 8, 38.86, -32.99, 0.46873, 2, 7, 114.73, -73.89, 0.80599, 8, 43.56, -69.46, 0.19401, 1, 7, -24.76, -70.33, 1, 1, 7, -48.67, -50.94, 1, 1, 7, -63.49, -33.02, 1, 1, 7, -66.67, 25.28, 1, 2, 7, 131.83, -6.27, 0.93432, 8, -4.53, -18.94, 0.06568, 1, 7, -24.48, -0.68, 1 ],
					"hull": 11,
					"edges": [ 0, 20, 0, 2, 2, 4, 4, 6, 6, 8, 8, 10, 10, 12, 12, 14, 14, 16, 16, 18, 18, 20 ],
					"width": 231,
					"height": 192
				}
			},
			"arm-red": {
				"arm_r": {
					"name": "red/arm-red",
					"type": "mesh",
					"uvs": [ 1, 1, 0, 1, 0, 0, 1, 0 ],
					"triangles": [ 1, 2, 3, 1, 3, 0 ],
					"vertices": [ 113.15, 105.53, 151.58, -24.93, -22.04, -76.07, -60.47, 54.39 ],
					"hull": 4,
					"edges": [ 0, 2, 2, 4, 4, 6, 0, 6 ],
					"width": 136,
					"height": 181
				}
			},
			"belt": {
				"belt": { "name": "red/belt", "x": 17.59, "y": -11.75, "rotation": -88.26, "width": 242, "height": 98 }
			},
			"belt-2": {
				"belt-2": {
					"name": "red/belt-2",
					"type": "mesh",
					"uvs": [ 1, 0.03785, 1, 0.04492, 0.83322, 0.37724, 0.82682, 0.51843, 0.82041, 0.65962, 0.84873, 0.80593, 0.87226, 0.92744, 0.56595, 1, 0.39232, 1, 0, 0.93062, 0, 0.91005, 0.00909, 0.85017, 0.09713, 0.78037, 0.15051, 0.65554, 0.17847, 0.49216, 0.17847, 0.3343, 0.12299, 0.10017, 0.13772, 0.0032, 0.42247, 0.86848, 0.46823, 0.6739, 0.50635, 0.3912, 0.52414, 0.16908 ],
					"triangles": [ 12, 13, 18, 12, 9, 10, 8, 12, 18, 12, 10, 11, 8, 9, 12, 19, 5, 18, 7, 5, 6, 7, 18, 5, 8, 18, 7, 3, 19, 20, 19, 14, 20, 4, 19, 3, 13, 14, 19, 18, 13, 19, 5, 19, 4, 15, 16, 21, 20, 15, 21, 20, 21, 2, 14, 15, 20, 3, 20, 2, 16, 17, 21, 21, 17, 0, 1, 21, 0, 2, 21, 1 ],
					"vertices": [ 1, 1, 19.25, -37.71, 1, 1, 1, 18.11, -37.75, 1, 3, 1, -36.3, -19.87, 0.46094, 33, 28.63, 45.69, 0.35693, 34, -12.71, 45.69, 0.18213, 4, 1, -59.18, -19.82, 0.14077, 33, 51.5, 44.83, 0.2775, 34, 10.16, 44.83, 0.55359, 35, -31.19, 44.83, 0.02814, 4, 1, -82.07, -19.76, 0.0282, 33, 74.37, 43.96, 0.07544, 34, 33.03, 43.96, 0.63235, 35, -8.32, 43.96, 0.26401, 4, 1, -105.66, -23.79, 0.00165, 33, 98.09, 47.16, 0.00571, 34, 56.74, 47.16, 0.30412, 35, 15.4, 47.16, 0.68852, 2, 34, 76.44, 49.81, 0.16184, 35, 35.1, 49.81, 0.83816, 2, 34, 88.02, 13.91, 0.01228, 35, 46.67, 13.91, 0.98772, 1, 35, 46.57, -6.4, 1, 2, 34, 76.44, -52.25, 0.07703, 35, 35.1, -52.25, 0.92297, 2, 34, 73.11, -52.23, 0.0799, 35, 31.76, -52.23, 0.9201, 2, 34, 63.41, -51.12, 0.10704, 35, 22.07, -51.12, 0.89296, 3, 33, 93.5, -40.76, 4.0E-5, 34, 52.16, -40.76, 0.2552, 35, 10.81, -40.76, 0.74476, 3, 33, 73.31, -34.41, 0.03179, 34, 31.97, -34.41, 0.71513, 35, -9.38, -34.41, 0.25308, 3, 33, 46.86, -31.01, 0.43941, 34, 5.52, -31.01, 0.55863, 35, -35.83, -31.01, 0.00196, 2, 33, 21.29, -30.88, 0.95894, 34, -20.06, -30.88, 0.04106, 1, 1, 6.05, 64.54, 1, 1, 1, 21.81, 63.3, 1, 1, 35, 25.28, -2.77, 1, 4, 1, -85.63, 21.36, 3.3E-4, 33, 76.47, 2.74, 7.8E-4, 34, 35.13, 2.74, 0.98054, 35, -6.21, 2.74, 0.01835, 3, 1, -39.72, 18.28, 0.04312, 33, 30.7, 7.44, 0.92261, 34, -10.64, 7.44, 0.03428, 2, 1, -3.69, 17.29, 0.36352, 33, -5.27, 9.7, 0.63648 ],
					"hull": 18,
					"edges": [ 0, 34, 0, 2, 2, 4, 12, 14, 14, 16, 16, 18, 18, 20, 32, 34, 32, 30, 30, 28, 28, 26, 26, 24, 20, 22, 24, 22, 10, 12, 8, 10, 4, 6, 6, 8 ],
					"width": 117,
					"height": 162
				}
			},
			"blink": {
				"blink": { "name": "red/blink", "x": 37.04, "y": 132.27, "rotation": -104.04, "width": 13, "height": 9 }
			},
			"blink2": {
				"blink2": { "name": "red/blink", "x": 19.46, "y": 40.59, "rotation": -104.04, "width": 13, "height": 9 }
			},
			"calf-back-red": {
				"calf_l": {
					"name": "red/calf-back-red",
					"type": "mesh",
					"uvs": [ 0.48387, 0, 0.98981, 0.24722, 0.99056, 0.75393, 0.99066, 0.82861, 0.7499, 1, 0.54421, 1, 0.31736, 0.96495, 0.27435, 0.86816, 0, 0.25078, 0, 0.09019, 0.23425, 0, 0.6708, 0.84443, 0.37915, 0.18583 ],
					"triangles": [ 12, 10, 0, 12, 0, 1, 12, 8, 9, 12, 9, 10, 11, 12, 1, 11, 1, 2, 11, 2, 3, 7, 8, 12, 7, 12, 11, 5, 6, 7, 11, 5, 7, 4, 11, 3, 5, 11, 4 ],
					"vertices": [ -17.49, 41.07, 34.79, 66.74, 91.66, 33.5, 100.04, 28.6, 107.58, -2.6, 97.6, -19.64, 82.66, -36.13, 69.72, -33.33, -12.85, -15.49, -30.86, -4.93, -29.61, 20.4, 86.29, 1.07, -1.73, 20.19 ],
					"hull": 11,
					"edges": [ 0, 20, 0, 2, 6, 8, 8, 10, 10, 12, 16, 18, 18, 20, 12, 14, 14, 16, 2, 4, 4, 6 ],
					"width": 96,
					"height": 130
				}
			},
			"calf-red": {
				"calf_r": {
					"name": "red/calf-red",
					"type": "mesh",
					"uvs": [ 0.56212, 0.10001, 0.88317, 0.43446, 0.98798, 0.54364, 0.99188, 0.75964, 0.99577, 0.97564, 0.75782, 1, 0.62355, 1, 0.50544, 0.87436, 0.12468, 0.4693, 0.02559, 0.36389, 0, 0.12016, 0, 0.00725, 0.47691, 0.01124, 0.29529, 0.2629, 0.83355, 0.80625 ],
					"triangles": [ 8, 9, 13, 1, 13, 0, 14, 1, 2, 14, 2, 3, 1, 7, 13, 7, 8, 13, 1, 14, 7, 14, 3, 4, 6, 7, 14, 5, 6, 14, 5, 14, 4, 13, 10, 11, 12, 13, 11, 13, 12, 0, 9, 10, 13 ],
					"vertices": [ 2, 23, 60.61, 24.13, 0.58502, 24, 6.17, 28.5, 0.41498, 2, 23, 87.92, 64.11, 0.14398, 24, 53.95, 36.32, 0.85602, 1, 24, 69.54, 38.87, 1, 1, 24, 87.63, 26.29, 1, 1, 24, 105.72, 13.7, 1, 1, 24, 92.8, -8.38, 1, 1, 24, 84.37, -20.01, 1, 2, 23, 139.38, 32.5, 0.07312, 24, 66.58, -22.73, 0.92688, 2, 23, 106.14, -15.06, 0.30886, 24, 9.22, -31.5, 0.69114, 2, 23, 97.5, -27.44, 0.37021, 24, -5.7, -33.78, 0.62979, 2, 23, 73.54, -34.64, 0.84808, 24, -27.44, -21.42, 0.15192, 2, 23, 62.22, -36.73, 0.93878, 24, -36.77, -14.66, 0.06122, 2, 23, 53.36, 13.52, 0.70208, 24, -6.51, 26.43, 0.29792, 2, 23, 82.13, -0.93, 0.48797, 24, 2.88, -4.37, 0.51203, 1, 24, 81.55, 9.78, 1 ],
					"hull": 13,
					"edges": [ 8, 10, 10, 12, 18, 20, 20, 22, 22, 24, 4, 6, 6, 8, 12, 14, 4, 2, 14, 16, 16, 18, 2, 0, 0, 24 ],
					"width": 107,
					"height": 102
				}
			},
			"eyeball": {
				"eyeball": { "name": "red/eyeball", "x": 40.44, "y": 133.48, "rotation": -104.04, "width": 37, "height": 41 }
			},
			"eyeball-back": {
				"eyeball-back": { "name": "red/eyeball-back", "x": 20.55, "y": 43.62, "rotation": -104.04, "width": 51, "height": 46 }
			},
			"eyes-closed-red": {
				"eyes-closed-red": {
					"name": "red/eyes-closed-red2",
					"path": "red/eyes-closed-red",
					"x": 29.76,
					"y": 82.55,
					"rotation": -104.04,
					"width": 157,
					"height": 51
				}
			},
			"finger-red": {
				"finger_r": {
					"name": "red/finger-red",
					"type": "mesh",
					"uvs": [ 1, 1, 0, 1, 0, 0, 1, 0 ],
					"triangles": [ 1, 2, 3, 1, 3, 0 ],
					"vertices": [ 13.42, 17.64, 54.22, -12.95, 17.63, -61.76, -23.17, -31.17 ],
					"hull": 4,
					"edges": [ 0, 2, 2, 4, 4, 6, 0, 6 ],
					"width": 51,
					"height": 61
				}
			},
			"foot_l": {
				"foot_l": {
					"name": "red/foot-red",
					"type": "mesh",
					"uvs": [ 0.84179, 0, 0.98798, 0.32938, 1, 0.51112, 1, 0.65199, 0.83227, 0.74406, 0.71261, 0.67496, 0.65801, 0.69958, 0.56119, 0.89286, 0.366, 1, 0.27498, 1, 0.0078, 0.91901, 0, 0.61716, 0, 0.53286, 0.1453, 0.13363, 0.29877, 0.10388, 0.47559, 0.13932, 0.55814, 0.11469, 0.66886, 0.07035, 0.70407, 0.02532, 0.83469, 0, 0.61577, 0.34323 ],
					"triangles": [ 5, 20, 18, 4, 5, 19, 6, 20, 5, 3, 4, 2, 4, 1, 2, 5, 18, 19, 20, 17, 18, 19, 0, 1, 1, 4, 19, 20, 16, 17, 11, 12, 13, 20, 15, 16, 7, 20, 6, 7, 15, 20, 9, 10, 11, 9, 13, 14, 8, 9, 14, 15, 8, 14, 9, 11, 13, 7, 8, 15 ],
					"vertices": [ 1, 19, 82.08, 12.11, 1, 2, 19, 127.51, 24.6, 0.73786, 20, -20.13, -14.84, 0.26214, 1, 20, -21.54, 3.47, 1, 1, 20, -20.49, 17.49, 1, 1, 20, 18.8, 23.77, 1, 2, 21, -14.83, 15.88, 0.01376, 20, 45.84, 14.83, 0.98624, 2, 21, -2.01, 16.52, 0.38242, 20, 58.59, 16.35, 0.61758, 2, 21, 22.86, 32.44, 0.99464, 20, 82.32, 33.92, 0.00536, 1, 21, 68.98, 36.62, 1, 1, 21, 89.78, 33.63, 1, 1, 21, 149.68, 16.85, 1, 1, 21, 147.17, -13.24, 1, 1, 21, 145.97, -21.57, 1, 1, 21, 107.1, -56.26, 1, 2, 21, 71.61, -54.16, 0.9996, 19, 27.66, -101.29, 4.0E-4, 3, 21, 31.72, -44.84, 0.91262, 19, 51.35, -67.86, 0.05037, 20, 96.41, -42.58, 0.03701, 3, 21, 12.5, -44.57, 0.66007, 19, 58.86, -50.18, 0.17339, 20, 77.22, -43.61, 0.16654, 3, 21, -13.42, -45.31, 0.16524, 19, 67.96, -25.89, 0.58344, 20, 51.41, -46.12, 0.25133, 3, 21, -22.11, -48.61, 0.0671, 19, 68.19, -16.6, 0.77093, 20, 42.97, -50, 0.16197, 2, 21, -52.31, -46.82, 1.0E-5, 19, 81.25, 10.69, 0.99999, 3, 21, 2.58, -20.09, 0.51658, 19, 85.27, -50.23, 0.13948, 20, 65.66, -19.86, 0.34394 ],
					"hull": 20,
					"edges": [ 0, 38, 0, 2, 2, 4, 4, 6, 16, 18, 18, 20, 20, 22, 22, 24, 24, 26, 6, 8, 8, 10, 10, 12, 14, 16, 12, 14, 26, 28, 28, 30, 30, 32, 32, 34, 36, 38, 34, 36 ],
					"width": 215,
					"height": 93
				}
			},
			"foot_r": {
				"foot_r": {
					"name": "red/foot-red",
					"type": "mesh",
					"uvs": [ 0.84179, 0, 0.98798, 0.32938, 1, 0.51112, 1, 0.65199, 0.83227, 0.74406, 0.71261, 0.67496, 0.65801, 0.69958, 0.56119, 0.89286, 0.366, 1, 0.27498, 1, 0.0078, 0.91901, 0, 0.61716, 0, 0.53286, 0.1453, 0.13363, 0.29877, 0.10388, 0.47559, 0.13932, 0.55814, 0.11469, 0.66886, 0.07035, 0.70407, 0.02532, 0.83469, 0, 0.61577, 0.34323 ],
					"triangles": [ 11, 12, 13, 7, 20, 6, 7, 15, 20, 9, 10, 11, 9, 13, 14, 8, 9, 14, 15, 8, 14, 9, 11, 13, 7, 8, 15, 1, 4, 19, 20, 16, 17, 5, 20, 18, 4, 5, 19, 6, 20, 5, 3, 4, 2, 20, 15, 16, 4, 1, 2, 5, 18, 19, 20, 17, 18, 19, 0, 1 ],
					"vertices": [ 1, 24, 71.36, 26.37, 1, 2, 24, 114.6, 33.86, 0.13714, 26, -35.34, -5.74, 0.86286, 1, 26, -35.63, 11.36, 1, 1, 26, -33.87, 24.34, 1, 1, 26, 3.02, 27.97, 1, 2, 26, 27.65, 18.14, 0.78886, 27, -18.73, 18.33, 0.21114, 2, 26, 39.59, 18.83, 0.25059, 27, -6.77, 18.55, 0.74941, 1, 27, 16.85, 32.63, 1, 1, 27, 59.91, 35.15, 1, 1, 27, 79.18, 31.75, 1, 1, 27, 134.44, 14.35, 1, 1, 27, 131.21, -13.59, 1, 1, 27, 129.85, -21.31, 1, 2, 26, 141.74, -48.16, 0.00795, 27, 92.64, -52.44, 0.99205, 3, 24, 10.71, -73.86, 0.00227, 26, 108.67, -46.46, 0.0724, 27, 59.66, -49.43, 0.92533, 3, 24, 35.67, -45, 0.09054, 26, 71.44, -38.07, 0.44022, 27, 22.8, -39.58, 0.46925, 3, 24, 44.23, -29.28, 0.27149, 26, 53.55, -37.96, 0.61197, 27, 4.92, -38.75, 0.11655, 2, 24, 54.85, -7.58, 0.84423, 26, 29.4, -38.84, 0.15577, 1, 24, 55.9, 1.01, 1, 1, 24, 70.46, 25.13, 1, 3, 24, 68.71, -31.71, 0.18174, 26, 44.13, -15.23, 0.80865, 27, -3.59, -15.67, 0.00962 ],
					"hull": 20,
					"edges": [ 0, 38, 0, 2, 2, 4, 4, 6, 16, 18, 18, 20, 20, 22, 22, 24, 24, 26, 6, 8, 8, 10, 10, 12, 14, 16, 12, 14, 26, 28, 28, 30, 30, 32, 32, 34, 36, 38, 34, 36 ],
					"width": 215,
					"height": 93
				}
			},
			"forearm-back-red": {
				"forearm_l": {
					"name": "red/forearm-back-red",
					"type": "mesh",
					"uvs": [ 1, 1, 0, 1, 0, 0, 1, 0 ],
					"triangles": [ 1, 2, 3, 1, 3, 0 ],
					"vertices": [ 99.91, 87.7, 119.88, -67.01, -32.86, -86.72, -52.82, 68 ],
					"hull": 4,
					"edges": [ 0, 2, 2, 4, 4, 6, 0, 6 ],
					"width": 156,
					"height": 154
				}
			},
			"forearm-red": {
				"forearm_r": {
					"name": "red/forearm-red",
					"type": "mesh",
					"uvs": [ 1, 1, 0, 1, 0, 0, 1, 0 ],
					"triangles": [ 1, 2, 3, 1, 3, 0 ],
					"vertices": [ 72.86, 121.37, 182.82, -2.98, 59.97, -111.62, -50, 12.73 ],
					"hull": 4,
					"edges": [ 0, 2, 2, 4, 4, 6, 0, 6 ],
					"width": 166,
					"height": 164
				}
			},
			"hand-2-red": {
				"hand-2-r": {
					"name": "red/hand-2-red",
					"type": "mesh",
					"uvs": [ 0.4481, 0, 0.76085, 0.0684, 1, 0.51838, 1, 0.7224, 0.68504, 1, 0.48848, 1, 0.01118, 0.96113, 0.01013, 0.22209, 0.28961, 0, 0.50752, 0.50331 ],
					"triangles": [ 9, 0, 1, 3, 4, 9, 4, 5, 9, 5, 6, 9, 9, 7, 8, 8, 0, 9, 9, 6, 7, 9, 2, 3, 9, 1, 2 ],
					"vertices": [ 2, 13, 8.57, -49.96, 0.07708, 12, 120.86, -50.66, 0.92292, 1, 12, 107.6, -24.82, 1, 2, 13, 1.47, 23.38, 0.65928, 12, 128.73, 22.6, 0.34072, 2, 13, 14.32, 40.53, 0.64525, 12, 144.78, 36.8, 0.35475, 1, 13, 54.49, 46.85, 1, 1, 13, 68.64, 36.23, 1, 1, 13, 100.56, 7.2, 1, 2, 13, 54.1, -54.94, 0.83992, 12, 164.44, -64.74, 0.16008, 2, 13, 19.98, -58.52, 0.63826, 12, 130.31, -61.35, 0.36174, 2, 13, 35.99, -4.47, 0.99114, 12, 156.91, -11.65, 0.00886 ],
					"hull": 9,
					"edges": [ 0, 16, 0, 2, 2, 4, 4, 6, 6, 8, 8, 10, 10, 12, 12, 14, 14, 16 ],
					"width": 90,
					"height": 105
				}
			},
			"hand-back-red": {
				"hand_l": {
					"name": "red/hand-back-red",
					"type": "mesh",
					"uvs": [ 0.65626, 0, 0.9054, 0.1045, 1, 0.58586, 1, 0.59958, 0.84786, 0.82213, 0.44745, 0.98644, 0.26553, 0.99939, 0.16501, 0.86882, 0.20388, 0.64169, 0.03839, 0.70436, 0.00183, 0.65687, 0.00874, 0.2272, 0.44265, 0, 0.70413, 0.51135, 0.30742, 0.4845 ],
					"triangles": [ 6, 7, 5, 7, 8, 5, 5, 8, 13, 5, 13, 4, 13, 8, 14, 4, 13, 3, 8, 10, 14, 13, 2, 3, 13, 14, 12, 14, 10, 11, 13, 1, 2, 14, 11, 12, 9, 10, 8, 1, 13, 0, 12, 0, 13 ],
					"vertices": [ 2, 8, 42.12, 12.06, 0.95745, 9, -36.12, 33.33, 0.04255, 2, 8, 61, 61.72, 0.41568, 9, 4.16, 67.97, 0.58432, 1, 9, 118.33, 42.9, 1, 2, 9, 121.4, 41.71, 0.34414, 10, 3.98, 60.8, 0.65586, 2, 9, 160.9, -4.23, 0.00404, 10, 64.21, 54.21, 0.99596, 1, 10, 128.89, -0.9, 1, 2, 9, 161.1, -121.69, 1.5E-4, 10, 144.55, -31.47, 0.99985, 3, 8, 260.74, -52.85, 1.1E-4, 9, 125.05, -128.01, 0.01286, 10, 122.53, -60.7, 0.98702, 3, 8, 205.74, -52.58, 0.0334, 9, 76.85, -101.54, 0.20328, 10, 69.23, -74.27, 0.76333, 3, 8, 224.64, -81.51, 0.02312, 9, 79.65, -135.98, 0.69761, 10, 94.8, -97.52, 0.27927, 3, 8, 214.22, -89.79, 0.02728, 9, 66.54, -138.28, 0.6653, 10, 86.79, -108.15, 0.30741, 1, 9, -29.17, -99.88, 1, 3, 8, 47.26, -27.77, 0.99521, 9, -50.61, -4.13, 4.2E-4, 10, -90.4, -90.13, 0.00437, 1, 10, 5.1, 1.3, 1, 3, 8, 165.84, -38.1, 0.06304, 9, 48.68, -69.77, 0.376, 10, 26.97, -70.3, 0.56096 ],
					"hull": 13,
					"edges": [ 0, 24, 0, 2, 2, 4, 4, 6, 6, 8, 8, 10, 10, 12, 20, 22, 22, 24, 12, 14, 14, 16, 18, 20, 16, 18 ],
					"width": 188,
					"height": 240
				}
			},
			"hand-red": {
				"hand-r": {
					"name": "red/hand-red",
					"type": "mesh",
					"uvs": [ 1, 1, 0, 1, 0, 0, 1, 0 ],
					"triangles": [ 1, 2, 3, 1, 3, 0 ],
					"vertices": [ 50.41, 58.65, 123.22, 4.07, 56.04, -85.55, -16.77, -30.96 ],
					"hull": 4,
					"edges": [ 0, 2, 2, 4, 4, 6, 0, 6 ],
					"width": 91,
					"height": 112
				}
			},
			"head-red": {
				"head": {
					"name": "red/head-red",
					"type": "mesh",
					"uvs": [ 1, 1, 0, 1, 0, 0, 1, 0 ],
					"triangles": [ 1, 2, 3, 1, 3, 0 ],
					"vertices": [ -186.21, -119.6, -99.63, 226.74, 308.8, 124.63, 222.22, -221.71 ],
					"hull": 4,
					"edges": [ 0, 2, 2, 4, 4, 6, 0, 6 ],
					"width": 357,
					"height": 421
				}
			},
			"pupil": {
				"pupil": { "name": "red/pupil", "x": -1.16, "y": -0.97, "rotation": -104.04, "width": 13, "height": 24 }
			},
			"pupil2": {
				"pupil2": { "name": "red/pupil", "x": -0.1, "y": -1.18, "rotation": -104.04, "width": 13, "height": 24 }
			},
			"shoulder-back": {
				"shoulder-back": { "name": "red/shoulder-back", "x": 111.74, "y": 51.88, "rotation": 15.48, "width": 230, "height": 213 }
			},
			"skirt": {
				"skirt": {
					"name": "red/skirt",
					"type": "mesh",
					"uvs": [ 0.80349, 0.02284, 0.86176, 0.18603, 0.92004, 0.34923, 1, 0.57315, 1, 0.61137, 0.87969, 0.70053, 0.75937, 0.7897, 0.5958, 0.91093, 0.47562, 1, 0.39971, 1, 0.27639, 0.92137, 0.1382, 0.73413, 0, 0.54689, 0, 0.53574, 0.03655, 0.44669, 0.12679, 0.22683, 0.21703, 0.00697, 0.73462, 0.44102, 0.82182, 0.38647, 0.18427, 0.52285, 0.34151, 0.70598, 0.50733, 0.77222, 0.6417, 0.64754 ],
					"triangles": [ 10, 20, 9, 11, 19, 10, 10, 19, 20, 12, 14, 11, 11, 14, 19, 16, 21, 20, 12, 13, 14, 14, 15, 19, 16, 20, 19, 19, 15, 16, 7, 22, 6, 6, 18, 5, 6, 17, 18, 4, 5, 3, 5, 18, 2, 5, 2, 3, 18, 1, 2, 18, 0, 1, 22, 17, 6, 22, 21, 16, 17, 22, 16, 17, 0, 18, 17, 16, 0, 8, 21, 7, 8, 9, 21, 9, 20, 21, 7, 21, 22 ],
					"vertices": [ 5, 1, 51.97, -106.74, 3.0E-4, 15, 100.63, 57.26, 0.37664, 16, -52.85, 22.07, 0.28967, 22, -112.15, -24.94, 0.09439, 23, -136.18, 108.28, 0.23899, 5, 1, 32.35, -127.04, 2.0E-4, 15, 124.02, 41.45, 0.34562, 16, -29.63, 38.12, 0.54301, 22, -130.03, -3.09, 0.04515, 23, -132.53, 136.28, 0.06601, 4, 1, 12.72, -147.34, 1.0E-4, 15, 147.42, 25.63, 0.21523, 16, -6.39, 54.17, 0.78464, 22, -147.91, 18.77, 4.0E-5, 3, 15, 179.51, 3.92, 0.06727, 16, 25.5, 76.19, 0.93273, 22, -172.44, 48.76, 1.0E-5, 3, 1, -18.95, -175.34, 0.00178, 15, 180.47, -0.72, 0.01711, 16, 30.17, 75.4, 0.98112, 4, 1, -31.24, -135.02, 0.05585, 15, 142.89, -19.79, 0.05657, 16, 34.29, 33.46, 0.8843, 23, -86.24, 180.59, 0.00328, 5, 1, -43.73, -94.71, 0.18985, 15, 105.35, -39.08, 0.11365, 16, 38.62, -8.52, 0.6701, 22, -89.07, 68.72, 0.00175, 23, -52.18, 155.67, 0.02465, 5, 1, -66.49, -39.91, 0.38964, 15, 55.31, -70.98, 0.15559, 16, 50.16, -66.73, 0.36562, 22, -31.99, 84.94, 0.00833, 23, -1.23, 125.23, 0.08082, 5, 1, -82.08, 0.36, 0.5104, 15, 18.35, -93.3, 0.11767, 16, 57.53, -109.28, 0.14106, 22, 9.82, 95.74, 0.01832, 23, 35.29, 102.19, 0.21255, 5, 1, -81.59, 26.01, 0.47128, 15, -7, -97.25, 0.0621, 16, 52.01, -134.33, 0.02258, 22, 35.23, 92.26, 0.0248, 23, 50.17, 81.3, 0.41923, 5, 1, -67.85, 67.97, 0.29528, 15, -50.7, -90.98, 0.01184, 16, 30.29, -172.77, 0.00382, 22, 75.31, 73.74, 0.02164, 23, 64.16, 39.43, 0.66742, 5, 1, -42.99, 115.36, 0.12045, 15, -101.68, -74.7, 0.00151, 16, -3.39, -214.35, 6.5E-4, 22, 119.49, 43.54, 0.01165, 23, 72.45, -13.44, 0.86574, 3, 1, -21.2, 162.75, 0.02556, 22, 164.02, 16.38, 0.00341, 23, 83.2, -64.48, 0.97103, 2, 22, 163.9, 15, 0.00414, 23, 82.12, -65.34, 0.99586, 3, 15, -142.55, -46.76, 2.0E-5, 22, 150.64, 5.07, 0.05336, 23, 65.79, -62.5, 0.94662, 5, 1, 19.77, 121.12, 1.0E-4, 15, -118.21, -13.88, 0.08952, 16, -66.06, -207.66, 0.02151, 22, 117.91, -19.47, 0.10261, 23, 25.49, -55.47, 0.78627, 5, 1, 47.94, 91.46, 2.0E-4, 15, -93.87, 19, 0.2287, 16, -87.86, -173.04, 0.10443, 22, 85.17, -44, 0.14359, 23, -14.81, -48.45, 0.52308, 1, 15, 88.35, 1.77, 1, 3, 15, 115.84, 14.37, 0.2552, 16, -7.37, 20.67, 0.74478, 22, -114.43, 20.51, 2.0E-5, 1, 23, 42.24, -17.47, 1, 4, 1, -42.02, 46.77, 0.34469, 16, 9.13, -146.91, 2.0E-4, 22, 51.26, 50.55, 0.14572, 23, 30.78, 41.05, 0.5094, 5, 1, -53.3, -9.5, 0.70239, 15, 23.08, -63.24, 0.17164, 16, 31.25, -93.96, 0.03483, 22, -3.32, 68.3, 0.00955, 23, 6.3, 92.95, 0.0816, 4, 1, -29.26, -54.42, 0.16192, 15, 63.17, -31.8, 0.64283, 16, 16.51, -45.18, 0.19258, 23, -39.78, 114.7, 0.00266 ],
					"hull": 17,
					"edges": [ 0, 32, 6, 8, 16, 18, 18, 20, 24, 26, 14, 16, 12, 14, 20, 22, 22, 24, 8, 10, 10, 12, 4, 6, 0, 2, 2, 4, 26, 28, 28, 30, 30, 32 ],
					"width": 338,
					"height": 124
				}
			},
			"spine": {
				"spine": {
					"name": "red/spine",
					"type": "mesh",
					"uvs": [ 0.64681, 0.29005, 0.6944, 0.30207, 0.746, 0.3479, 0.79759, 0.39372, 0.76748, 0.48023, 0.73859, 0.53429, 0.7097, 0.58836, 0.68343, 0.63753, 0.65786, 0.68537, 0.52296, 0.70392, 0.44341, 0.66918, 0.42327, 0.63469, 0.38716, 0.57284, 0.35207, 0.51273, 0.32761, 0.47083, 0.30315, 0.42892, 0.31231, 0.31949, 0.36756, 0.30873, 0.46728, 0.28932, 0.56699, 0.2699, 0.54428, 0.63787, 0.52013, 0.58762, 0.51047, 0.51063, 0.50564, 0.42554, 0.53655, 0.33721, 0.63121, 0.40528, 0.38588, 0.40852 ],
					"triangles": [ 26, 17, 18, 26, 18, 24, 16, 17, 26, 23, 26, 24, 15, 16, 26, 14, 15, 26, 13, 14, 26, 26, 22, 13, 22, 26, 23, 10, 11, 20, 8, 20, 7, 6, 21, 22, 12, 22, 21, 11, 12, 21, 7, 21, 6, 20, 21, 7, 11, 21, 20, 9, 10, 20, 9, 20, 8, 12, 13, 22, 5, 6, 22, 24, 18, 19, 0, 24, 19, 23, 24, 25, 22, 23, 25, 25, 0, 1, 25, 1, 2, 25, 24, 0, 3, 25, 2, 4, 25, 3, 5, 25, 4, 22, 25, 5 ],
					"vertices": [ 2, 5, 46.56, 81.99, 0.6862, 2, 240.18, -62.13, 0.3138, 2, 5, 84.37, 81.16, 0.89273, 2, 232.36, -99.13, 0.10727, 2, 5, 133.31, 51.58, 0.99616, 2, 194.24, -141.75, 0.00384, 3, 5, 182.25, 22.01, 0.99992, 1, 272.4, -192.49, 4.0E-5, 15, 146.95, 289.21, 4.0E-5, 4, 5, 181.29, -60.5, 0.7712, 2, 75.21, -168.16, 0.12414, 1, 192.48, -171.96, 0.05986, 15, 140.55, 206.94, 0.0448, 4, 5, 173.58, -115.19, 0.35714, 2, 22.9, -150.45, 0.18198, 1, 141.19, -151.47, 0.34631, 15, 129.25, 152.88, 0.11457, 4, 5, 165.89, -169.95, 0.13015, 2, -29.5, -132.76, 0.11602, 1, 89.82, -130.98, 0.51603, 15, 117.96, 98.74, 0.2378, 4, 5, 158.33, -217.48, 0.0551, 2, -74.8, -116.53, 0.05135, 1, 45.46, -112.35, 0.24629, 15, 107.28, 51.82, 0.64726, 4, 5, 150.51, -261.78, 0.00587, 2, -116.89, -100.64, 0.0035, 1, 4.29, -94.21, 0.03703, 15, 96.55, 8.13, 0.9536, 2, 1, -27.54, 7.89, 0.92961, 22, 10.95, 40.69, 0.07039, 5, 2, -116.13, 63.21, 3.4E-4, 1, 13.86, 69.36, 0.04888, 15, -66.21, -10.75, 6.0E-5, 22, 67.18, -7.57, 0.94734, 6, 123.34, 259.19, 0.00339, 5, 2, -89.23, 80.94, 0.01988, 1, 41.67, 85.62, 0.27372, 15, -87.04, 13.83, 3.0E-5, 22, 80.1, -37.09, 0.67794, 6, 134.57, 228.99, 0.02844, 5, 2, -36.79, 112.97, 0.18649, 1, 95.75, 114.79, 0.3605, 15, -125.12, 62.05, 1.0E-5, 22, 102.78, -94.2, 0.26686, 6, 153.98, 170.69, 0.18614, 5, 2, 17.99, 144.3, 0.23822, 1, 152.14, 143.13, 0.15744, 15, -162.8, 112.69, 1.0E-5, 22, 124.36, -153.5, 0.08895, 6, 172.18, 110.26, 0.51538, 4, 2, 55.61, 166.12, 0.13011, 1, 190.88, 162.89, 0.05925, 22, 139.48, -194.27, 0.03336, 6, 184.97, 68.7, 0.77728, 4, 2, 92.5, 187.89, 0.03631, 1, 228.89, 182.65, 0.01548, 22, 154.68, -234.33, 0.00906, 6, 197.89, 27.85, 0.93915, 1, 6, 176.82, -69.6, 1, 2, 2, 205.45, 148.21, 0.01586, 6, 133.81, -73.27, 0.98414, 2, 2, 229.37, 74.07, 0.34347, 6, 56.19, -79.9, 0.65653, 3, 5, -16.85, 83.39, 0.17303, 2, 253.29, -0.07, 0.73088, 6, -21.43, -86.52, 0.09609, 3, 5, 58.57, -255.04, 2.4E-4, 1, 32.68, -6.51, 0.94168, 15, 5.26, 20.92, 0.05808, 4, 2, -49.49, 10.59, 1.4E-4, 1, 77.57, 13.24, 0.94908, 22, 4.03, -64.33, 0.04596, 6, 57.08, 206.09, 0.00482, 4, 2, 31.49, 24.43, 0.49824, 1, 159.17, 22.7, 0.46379, 22, 3.93, -146.47, 0.00827, 6, 52.34, 124.08, 0.0297, 4, 2, 108.7, 34.6, 0.62298, 1, 236.82, 28.71, 2.4E-4, 22, 0.87, -224.3, 0.0011, 6, 44.88, 46.56, 0.37568, 2, 2, 190.52, 17.89, 0.63524, 6, 10.19, -29.4, 0.36476, 4, 5, 63.02, -21.91, 0.79484, 2, 135.03, -59.07, 0.20284, 1, 258.07, -66.24, 0.00107, 15, 25.09, 253.25, 0.00126, 4, 2, 116.35, 126.72, 0.03362, 1, 249.41, 120.28, 0.0065, 22, 90.35, -247.45, 0.0039, 6, 132.91, 18.39, 0.95599 ],
					"hull": 20,
					"edges": [ 6, 8, 16, 18, 18, 20, 30, 32, 14, 16, 12, 14, 8, 10, 10, 12, 20, 22, 22, 24, 24, 26, 26, 28, 28, 30, 32, 34, 34, 36, 36, 38, 2, 0, 0, 38, 2, 4, 4, 6 ],
					"width": 761,
					"height": 907
				}
			},
			"thigh-back-red": {
				"thigh_l": {
					"name": "red/thigh-back-red",
					"type": "mesh",
					"uvs": [ 1, 1, 0, 1, 0, 0, 1, 0 ],
					"triangles": [ 1, 2, 3, 1, 3, 0 ],
					"vertices": [ 124.97, 41.11, 105.63, -73.26, -70.87, -43.42, -51.53, 70.96 ],
					"hull": 4,
					"edges": [ 0, 2, 2, 4, 4, 6, 0, 6 ],
					"width": 116,
					"height": 179
				}
			},
			"thigh-red": {
				"thigh_r": { "name": "red/thigh-red", "x": 24.75, "y": -2.34, "rotation": 128.33, "width": 142, "height": 147 }
			}
		}
	},
	{
		"name": "shadow/soft",
		"attachments": {
			"shadow_hard": {
				"shadow": { "name": "shadow/shadow_soft", "width": 112, "height": 56 }
			}
		}
	},
	{
		"name": "weapon/sword",
		"bones": [ "sword" ],
		"attachments": {
			"hand-sword-red": {
				"weapon": { "name": "red/hand-sword-red", "x": 327.83, "y": 0.45, "rotation": -95.78, "width": 197, "height": 668 }
			}
		}
	}
],
"events": {
	"hit": {},
	"impact": {}
},
"animations": {
	"attack": {
		"slots": {
			"eyes-closed-red": {
				"attachment": [
					{ "time": 0.5667, "name": "eyes-closed-red" },
					{ "time": 0.6333, "name": null }
				]
			}
		},
		"bones": {
			"head": {
				"rotate": [
					{},
					{ "time": 0.3667, "angle": -17.5 },
					{ "time": 0.6333, "angle": -5.53 },
					{ "time": 1.2 }
				]
			},
			"hand_r": {
				"rotate": [
					{ "angle": -20.01 },
					{ "time": 0.2667, "angle": -153.89 },
					{ "time": 0.3333, "angle": -142.34 },
					{ "time": 0.4, "angle": -148.97 },
					{ "time": 0.4333, "angle": -86.55 },
					{ "time": 0.4667, "angle": 12.01 },
					{ "time": 0.5333, "angle": 71.39 },
					{ "time": 0.6333, "angle": 67.87 },
					{ "time": 1, "angle": 66.39 },
					{ "time": 1.0667, "angle": 67.08 },
					{ "time": 1.2, "angle": -20.01 }
				]
			},
			"foot_r": {
				"translate": [
					{ "x": -10.14, "y": -12.46 },
					{ "time": 0.3667, "x": -10.14, "y": -30.42 },
					{ "time": 0.5333, "x": -61.01, "y": -30.42 },
					{ "time": 1.2, "x": -10.14, "y": -12.46 }
				]
			},
			"chest": {
				"rotate": [
					{},
					{ "time": 0.2333, "angle": -6.35, "curve": "stepped" },
					{ "time": 0.3667, "angle": -6.35 },
					{ "time": 0.5, "angle": 21.33 },
					{ "time": 0.7, "angle": 29.35, "curve": "stepped" },
					{ "time": 0.8667, "angle": 29.35 },
					{ "time": 1.2 }
				],
				"translate": [
					{},
					{ "time": 0.5, "x": -19.46, "y": -1.81 },
					{ "time": 1.2 }
				],
				"scale": [
					{},
					{ "time": 0.5, "x": 1.09, "y": 1.09 },
					{ "time": 1.2 }
				]
			},
			"hand_l": {
				"translate": [
					{ "x": -57.79, "y": 31.97 },
					{ "time": 0.5667, "x": 12.46, "y": 36.23 },
					{ "time": 1.2, "x": -57.79, "y": 31.97 }
				]
			},
			"hand_r2": {
				"translate": [
					{},
					{ "time": 0.1667, "x": 79.56, "y": 314.53 },
					{ "time": 0.2667, "x": 299.34, "y": 380.42 },
					{ "time": 0.3333, "x": 411.06, "y": 337.33, "curve": "stepped" },
					{ "time": 0.4, "x": 411.06, "y": 337.33 },
					{ "time": 0.4333, "x": 131.23, "y": 479.05 },
					{ "time": 0.4667, "x": -152.36, "y": 149.4 },
					{ "time": 0.5, "x": -161.08, "y": -43.22 },
					{ "time": 0.5333, "x": 104.57, "y": -136.89 },
					{ "time": 0.6333, "x": 311.66, "y": -48.57 },
					{ "time": 0.9, "x": 393.19, "y": 35.63 },
					{ "time": 1.2 }
				]
			},
			"hand_l_2": {
				"rotate": [
					{},
					{ "time": 0.3667, "angle": -15.54 },
					{ "time": 0.5667, "angle": 18.71 },
					{ "time": 1.2 }
				]
			},
			"stomach": {
				"rotate": [
					{},
					{ "time": 0.3667, "angle": -4.42 },
					{ "time": 1.2 }
				],
				"translate": [
					{},
					{ "time": 0.2333, "x": 40.09, "y": 11.64 },
					{ "time": 0.3667, "x": 65.09, "y": 16.82 },
					{ "time": 0.5, "x": -104.69, "y": -56.89 },
					{ "time": 1.2 }
				]
			},
			"shoulder_r": {
				"rotate": [
					{},
					{ "time": 0.3667, "angle": -29.42 },
					{ "time": 0.5 }
				],
				"translate": [
					{},
					{ "time": 0.3667, "x": -15.08, "y": -51.17 },
					{ "time": 0.5, "x": -3.09, "y": 30.91 },
					{ "time": 1.2 }
				]
			},
			"foot_l2": {
				"translate": [
					{ "time": 0.4 },
					{ "time": 0.5333, "x": 34.17, "y": -67.88, "curve": "stepped" },
					{ "time": 0.6667, "x": 34.17, "y": -67.88 },
					{ "time": 1, "x": 6.47, "y": -1.69 },
					{ "time": 1.2 }
				]
			},
			"bone15": {
				"translate": [
					{},
					{ "time": 0.3667, "x": 0.45, "y": 7.7 },
					{ "time": 0.5667, "x": 1.06, "y": -12.61 },
					{ "time": 1.2 }
				]
			},
			"foot_r2": {
				"translate": [
					{},
					{ "time": 0.3333, "x": -19.56, "y": -61.33 },
					{ "time": 0.4333, "x": 14.93, "y": 5.25 },
					{ "time": 1.2 }
				]
			},
			"foot_r3": {
				"translate": [
					{},
					{ "time": 0.3333, "x": -23.46, "y": -38.76 },
					{ "time": 0.4333, "x": 14.93, "y": 5.25 },
					{ "time": 1.2 }
				]
			},
			"shadow": {
				"translate": [
					{},
					{ "time": 0.3333, "x": 14.46 },
					{ "time": 0.5667, "x": -53.52 },
					{ "time": 1 }
				]
			}
		},
		"ik": {
			"hand_l": [
				{ "mix": 0.6, "bendPositive": false }
			],
			"hand_r": [
				{ "mix": 0.6, "bendPositive": false }
			]
		},
		"drawOrder": [
			{
				"time": 0.0667,
				"offsets": [
					{ "slot": "hand-sword-red", "offset": -12 }
				]
			},
			{ "time": 1.2 }
		],
		"events": [
			{ "time": 0.5, "name": "impact" }
		]
	},
	"damage": {
		"slots": {
			"eyes-closed-red": {
				"attachment": [
					{ "time": 0.0333, "name": "eyes-closed-red" },
					{ "time": 0.2, "name": null }
				]
			}
		},
		"bones": {
			"head": {
				"rotate": [
					{},
					{ "time": 0.0667, "angle": -27.53 },
					{ "time": 0.1333, "angle": -41.53 },
					{ "time": 0.2, "angle": -64.33 },
					{ "time": 0.3, "angle": -51.33 },
					{ "time": 0.5333 }
				]
			},
			"hand_r": {
				"rotate": [
					{},
					{ "time": 0.2, "angle": -12.62 },
					{ "time": 0.3333, "angle": -22.15 },
					{ "time": 0.5333 }
				]
			},
			"foot_r": {
				"translate": [
					{ "x": -10.14, "y": -12.46 },
					{ "time": 0.1333, "x": 27.2, "y": -15.86 },
					{ "time": 0.5333, "x": -10.14, "y": -12.46 }
				]
			},
			"chest": {
				"rotate": [
					{},
					{ "time": 0.0667, "angle": -6.72 },
					{ "time": 0.2, "angle": -16.98 },
					{ "time": 0.5333 }
				]
			},
			"hand_l": {
				"translate": [
					{ "x": -57.79, "y": 31.97 },
					{ "time": 0.2, "x": 219.86, "y": -35.75 },
					{ "time": 0.5333, "x": -57.79, "y": 31.97 }
				]
			},
			"hand_r2": {
				"translate": [
					{ "x": 4.48, "y": -2.08 },
					{ "time": 0.1333, "x": 232.12, "y": 94.57 },
					{ "time": 0.2333, "x": 253.35, "y": 78.71 },
					{ "time": 0.5333 }
				]
			},
			"hand_l_2": {
				"rotate": [
					{},
					{ "time": 0.2, "angle": -29.07 },
					{ "time": 0.5333 }
				]
			},
			"stomach": {
				"rotate": [
					{},
					{ "time": 0.1333, "angle": -10.49 },
					{ "time": 0.2, "angle": -16.79 },
					{ "time": 0.5333 }
				],
				"translate": [
					{},
					{ "time": 0.0667, "x": 86.72, "y": -17.34 },
					{ "time": 0.1333, "x": 105.99, "y": -25.53 },
					{ "time": 0.5333 }
				]
			},
			"neck": {
				"rotate": [
					{},
					{ "time": 0.1, "angle": -30.15 },
					{ "time": 0.2, "angle": -20.9 },
					{ "time": 0.5333 }
				]
			},
			"bone15": {
				"translate": [
					{},
					{ "time": 0.1, "x": -2.65, "y": 15.64 },
					{ "time": 0.5333 }
				]
			},
			"foot_r3": {
				"rotate": [
					{},
					{ "time": 0.1333, "angle": -29.63 },
					{ "time": 0.3333 }
				],
				"translate": [
					{},
					{ "time": 0.1333, "x": -1.72, "y": -17.05 },
					{ "time": 0.3333 }
				]
			},
			"foot_r2": {
				"rotate": [
					{ "angle": 0.69 }
				],
				"translate": [
					{},
					{ "time": 0.1333, "x": 6.12, "y": -1.72 },
					{ "time": 0.3333 }
				]
			},
			"hand_l_1": {
				"rotate": [
					{},
					{ "time": 0.2, "angle": 30.74 },
					{ "time": 0.5333 }
				]
			},
			"shadow": {
				"translate": [
					{},
					{ "time": 0.1667, "x": 24.59 },
					{ "time": 0.5333 }
				],
				"scale": [
					{},
					{ "time": 0.1667, "x": 0.87 },
					{ "time": 0.5333 }
				]
			}
		},
		"ik": {
			"hand_l": [
				{ "mix": 0.6, "bendPositive": false }
			],
			"hand_r": [
				{ "mix": 0.6, "bendPositive": false }
			]
		},
		"events": [
			{ "time": 0.1, "name": "hit" }
		]
	},
	"death": {
		"slots": {
			"eyes-closed-red": {
				"attachment": [
					{ "time": 0.3667, "name": "eyes-closed-red" }
				]
			}
		},
		"bones": {
			"head": {
				"rotate": [
					{},
					{ "time": 0.1, "angle": 12.9 },
					{ "time": 0.1667, "angle": 24.08 },
					{ "time": 0.3667, "angle": -106.03 },
					{ "time": 0.5333, "angle": -92.55 },
					{ "time": 0.6333, "angle": -106.03 }
				]
			},
			"hand_r": {
				"rotate": [
					{},
					{ "time": 0.0667, "angle": -7.24 },
					{ "time": 0.3333, "angle": -119.54 }
				]
			},
			"foot_r": {
				"rotate": [
					{},
					{ "time": 0.2333, "angle": -6.72 },
					{ "time": 0.4667, "angle": -56.38 }
				],
				"translate": [
					{ "x": -10.14, "y": -12.46 },
					{ "time": 0.1, "x": 55.33, "y": -18.89 },
					{ "time": 0.3, "x": 248.03, "y": 15.06 },
					{ "time": 0.4, "x": 225.45, "y": 3.24 },
					{ "time": 0.5667, "x": 225.45, "y": -44.48 }
				]
			},
			"chest": {
				"rotate": [
					{},
					{ "time": 0.0667, "angle": 13.54, "curve": "stepped" },
					{ "time": 0.3667, "angle": 13.54 },
					{ "time": 0.4333, "angle": 23.65 },
					{ "time": 0.5333, "angle": 4.69 }
				]
			},
			"hand_l": {
				"translate": [
					{ "x": -57.79, "y": 31.97 },
					{ "time": 0.0667, "x": 41.16, "y": 119.35 },
					{ "time": 0.4, "x": 245.45, "y": -185.93 },
					{ "time": 0.6667, "x": 158.2, "y": -71.78 }
				]
			},
			"hand_r2": {
				"translate": [
					{ "x": 4.48, "y": -2.08 },
					{ "time": 0.1, "x": 190.45, "y": 94.57 },
					{ "time": 0.4667, "x": 740.84, "y": -301.53 }
				]
			},
			"stomach": {
				"rotate": [
					{},
					{ "time": 0.3667, "angle": -84.88 },
					{ "time": 0.6333, "angle": -87.85 }
				],
				"translate": [
					{},
					{ "time": 0.0667, "x": 86.72, "y": -17.34 },
					{ "time": 0.1, "x": 105.99, "y": -25.53 },
					{ "time": 0.3667, "x": 381.37, "y": -189.15 },
					{ "time": 0.4333, "x": 378.37, "y": -138.43 },
					{ "time": 0.6333, "x": 381.37, "y": -152.12, "curve": "stepped" },
					{ "time": 0.8333, "x": 381.37, "y": -152.12 }
				]
			},
			"foot_r2": {
				"translate": [
					{ "time": 0.1667 },
					{ "time": 0.3, "x": -0.37, "y": -13.42 }
				]
			},
			"neck": {
				"rotate": [
					{},
					{ "time": 0.0667, "angle": 33.96, "curve": "stepped" },
					{ "time": 0.1667, "angle": 33.96 },
					{ "time": 0.3667, "angle": -62.64 },
					{ "time": 0.4333, "angle": -12.26 },
					{ "time": 0.5333, "angle": -34.07 }
				]
			},
			"foot_l": {
				"rotate": [
					{ "time": 0.0667 },
					{ "time": 0.3667, "angle": -49.64 }
				],
				"translate": [
					{},
					{ "time": 0.2, "x": -76.31, "y": -16.07 },
					{ "time": 0.4, "x": -36.1, "y": -32.15 }
				]
			},
			"bone15": {
				"translate": [
					{},
					{ "time": 0.3667, "x": 7.65, "y": 38.31 }
				]
			},
			"shoulder_l": {
				"translate": [
					{},
					{ "time": 0.3667, "x": 13.35, "y": 62.16 }
				]
			},
			"shoulder_r": {
				"translate": [
					{},
					{ "time": 0.3667, "x": 6.21, "y": -64.64 }
				]
			},
			"foot_r3": {
				"rotate": [
					{},
					{ "time": 0.3667, "angle": -13.81 }
				],
				"translate": [
					{},
					{ "time": 0.3667, "x": -0.01, "y": -35.48 }
				]
			},
			"foot_l3": {
				"rotate": [
					{},
					{ "time": 0.2667, "angle": -26.12 },
					{ "time": 0.5667, "angle": 0.4 }
				]
			},
			"shadow": {
				"translate": [
					{},
					{ "time": 0.3667, "x": 523.89, "y": -22.84 }
				],
				"scale": [
					{},
					{ "time": 0.3667, "x": 2.019 }
				]
			}
		},
		"ik": {
			"hand_l": [
				{ "mix": 0.6, "bendPositive": false }
			],
			"hand_r": [
				{ "mix": 0.6, "bendPositive": false }
			]
		},
		"deform": {
			"body/green": {
				"foot_r": {
					"foot_r": [
						{
							"time": 0.5667,
							"vertices": [ -0.98102, 0.18996, -0.98102, 0.18996, -0.41063, -0.91095, -0.41063, -0.91095, -0.41063, -0.91095, -0.41063, -0.91095, -0.41063, -0.91095, -0.17245, -0.98424, -0.41063, -0.91095, -0.17245, -0.98424, -0.17245, -0.98424, -0.17245, -0.98424, -0.17245, -0.98424, -0.17245, -0.98424, -0.17245, -0.98424, -0.17245, -0.98424, -0.41063, -0.91095, -0.17245, -0.98424, -0.98102, 0.18996, -0.41063, -0.91095, -0.17245, -0.98424, -0.98102, 0.18996, -0.41063, -0.91095, -0.17245, -0.98424, -0.98102, 0.18996, -0.41063, -0.91095, -0.17245, -0.98424, -0.98102, 0.18996, -0.41063, -0.91095, -0.98102, 0.18996, -0.98102, 0.18996, -0.98102, 0.18996, -0.41063, -0.91095, -0.17245, -0.98424 ]
						}
					]
				}
			},
			"body/red": {
				"foot_r": {
					"foot_r": [
						{
							"time": 0.5667,
							"vertices": [ -0.98102, 0.18996, -0.98102, 0.18996, -0.41063, -0.91095, -0.41063, -0.91095, -0.41063, -0.91095, -0.41063, -0.91095, -0.41063, -0.91095, -0.17245, -0.98424, -0.41063, -0.91095, -0.17245, -0.98424, -0.17245, -0.98424, -0.17245, -0.98424, -0.17245, -0.98424, -0.17245, -0.98424, -0.17245, -0.98424, -0.17245, -0.98424, -0.41063, -0.91095, -0.17245, -0.98424, -0.98102, 0.18996, -0.41063, -0.91095, -0.17245, -0.98424, -0.98102, 0.18996, -0.41063, -0.91095, -0.17245, -0.98424, -0.98102, 0.18996, -0.41063, -0.91095, -0.17245, -0.98424, -0.98102, 0.18996, -0.41063, -0.91095, -0.98102, 0.18996, -0.98102, 0.18996, -0.98102, 0.18996, -0.41063, -0.91095, -0.17245, -0.98424 ]
						}
					]
				}
			}
		},
		"events": [
			{ "time": 0.1, "name": "hit" }
		]
	},
	"idle": {
		"slots": {
			"eyes-closed-red": {
				"attachment": [
					{ "time": 1.1, "name": "eyes-closed-red" },
					{ "time": 1.2, "name": null }
				]
			}
		},
		"bones": {
			"head": {
				"rotate": [
					{},
					{ "time": 1.2333, "angle": -5.53 },
					{ "time": 2.3333 }
				]
			},
			"foot_r": {
				"translate": [
					{ "x": -10.14, "y": -12.46 }
				]
			},
			"chest": {
				"rotate": [
					{},
					{ "time": 1, "angle": -2.7 },
					{ "time": 2.3333 }
				],
				"scale": [
					{},
					{ "time": 1, "x": 1.09, "y": 1.09 },
					{ "time": 2.3333 }
				]
			},
			"hand_l": {
				"translate": [
					{ "x": -57.79, "y": 31.97 }
				]
			},
			"hand_r2": {
				"translate": [
					{ "x": 4.48, "y": -2.08 },
					{ "time": 1.3, "x": 23.41, "y": 33.94 },
					{ "time": 2.3333, "x": 4.48, "y": -2.08 }
				]
			},
			"hand_l_2": {
				"rotate": [
					{},
					{ "time": 1.1, "angle": -10.94 },
					{ "time": 2.3333 }
				]
			},
			"stomach": {
				"translate": [
					{},
					{ "time": 0.9667, "x": 11.71, "y": 1.95 },
					{ "time": 2.3333 }
				]
			},
			"hand_r": {
				"rotate": [
					{},
					{ "time": 1, "angle": -16.45 },
					{ "time": 2.3333 }
				]
			}
		},
		"ik": {
			"hand_l": [
				{ "mix": 0.6, "bendPositive": false }
			],
			"hand_r": [
				{ "mix": 0.6, "bendPositive": false }
			]
		}
	}
}
}